Workbook
Name SegmentaciónDeDatos_Días_Visita: #N/A
Name SegmentaciónDeDatos_Modo_de_Compra: #N/A
Name SegmentaciónDeDatos_Parque_Origen: #N/A

Sheet Comisiones HEROIC
A1: Parque Origen | B1: Comisión | E1: Precio por día | F1: Hotel
A2: Puente Roto | B2: 12 | E2: 105 | F2: OI Hotels
A3: Monte Japón | B3: 16 | E3: 110 | F3: Elton Hotel
A4: Rio de Castores | B4: 13 | E4: 100 | F4: Ridossan Hotel
A5: Piedra Angular | B5: 25 | E5: 115 | F5: Haiit Hotel
A6: Villa Parque | B6: 22 | E6: 75 | F6: Ski Inn
A7: El cielo | B7: 14
A8: Cascadas Congeladas | B8: 14
A9: Rio Vinoblanco | B9: 16
A10: Molinos Blancos | B10: 24
A11: Montaña Rio Rojo | B11: 17

Sheet Ventas Pases
A1: Momento de Compra | B1: Año | C1: Fecha Compra | D1: Modo de Compra | E1: Fecha Inicial de Pase | F1: Días Visita | G1: Parque Origen | H1: Numero de Pase | I1: Precio Venta | J1: Costo x dia | K1: Hotel | L1: Comisiones | M1: Dias de regalo | N1: Renta | O1: Costos lift
A2: Temporada Regular | B2: 2019 | C2: 43471 | D2: En Línea | E2: 43537 | F2: 9 | G2: Valle Silbador | H2: WSP-0001 | I2: 1080 | J2: =IFERROR('Ventas Pases'!$I2/'Ventas Pases'!$F2,"PASE") -> 120 | K2: =IFERROR(VLOOKUP('Ventas Pases'!$J2,'Comisiones HEROIC'!$E$1:$F$6,2,0),"") | L2: =IF('Ventas Pases'!$D2="Red HEROIC",IFERROR(VLOOKUP('Ventas Pases'!$G2,'Comisiones HEROIC'!$A$1:$B$11,2,0),15),IF('Ventas Pases'!$D2="Red HEROIC",15,0)) -> 0 | M2: =IF(pases[[#This Row],[Días Visita]]<7,0,IF(pases[[#This Row],[Días Visita]]<9,1,IF(pases[[#This Row],[Días Visita]]="Ilimitados",0,2))) -> 2 | N2: =IF(AND('Ventas Pases'!$A2="Fuera de Temporada",'Ventas Pases'!$B2=2019,pases[[#This Row],[Modo de Compra]]="Paquete"),30,0) -> 0 | O2: =-SUMIF(lift[Número de pase],pases[[#This Row],[Numero de Pase]],lift[Costo]) -> 0
A3: Temporada Regular | B3: 2019 | C3: 43427 | D3: En Línea | E3: 43419 | F3: Ilimitados | G3: Valle Silbador | H3: WSP-0002 | I3: 1950 | J3: =IFERROR('Ventas Pases'!$I3/'Ventas Pases'!$F3,"PASE") -> PASE | K3: =IFERROR(VLOOKUP('Ventas Pases'!$J3,'Comisiones HEROIC'!$E$1:$F$6,2,0),"") | L3: =IF('Ventas Pases'!$D3="Red HEROIC",IFERROR(VLOOKUP('Ventas Pases'!$G3,'Comisiones HEROIC'!$A$1:$B$11,2,0),15),IF('Ventas Pases'!$D3="Red HEROIC",15,0)) -> 0 | M3: =IF(pases[[#This Row],[Días Visita]]<7,0,IF(pases[[#This Row],[Días Visita]]<9,1,IF(pases[[#This Row],[Días Visita]]="Ilimitados",0,2))) -> 0 | N3: =IF(AND('Ventas Pases'!$A3="Fuera de Temporada",'Ventas Pases'!$B3=2019,pases[[#This Row],[Modo de Compra]]="Paquete"),30,0) -> 0 | O3: =-SUMIF(lift[Número de pase],pases[[#This Row],[Numero de Pase]],lift[Costo]) -> -368
A4: Fuera de Temporada | B4: 2018 | C4: 43396 | D4: Red HEROIC | E4: 42834 | F4: 6 | G4: Puente Roto | H4: WSP-0003 | I4: 840 | J4: =IFERROR('Ventas Pases'!$I4/'Ventas Pases'!$F4,"PASE") -> 140 | K4: =IFERROR(VLOOKUP('Ventas Pases'!$J4,'Comisiones HEROIC'!$E$1:$F$6,2,0),"") | L4: =IF('Ventas Pases'!$D4="Red HEROIC",IFERROR(VLOOKUP('Ventas Pases'!$G4,'Comisiones HEROIC'!$A$1:$B$11,2,0),15),IF('Ventas Pases'!$D4="Red HEROIC",15,0)) -> 12 | M4: =IF(pases[[#This Row],[Días Visita]]<7,0,IF(pases[[#This Row],[Días Visita]]<9,1,IF(pases[[#This Row],[Días Visita]]="Ilimitados",0,2))) -> 0 | N4: =IF(AND('Ventas Pases'!$A4="Fuera de Temporada",'Ventas Pases'!$B4=2019,pases[[#This Row],[Modo de Compra]]="Paquete"),30,0) -> 0 | O4: =-SUMIF(lift[Número de pase],pases[[#This Row],[Numero de Pase]],lift[Costo]) -> 0
A5: Temporada Regular | B5: 2018 | C5: 43429 | D5: Paquete | E5: 43125 | F5: 7 | G5: Valle Silbador | H5: WSP-0004 | I5: 805 | J5: =IFERROR('Ventas Pases'!$I5/'Ventas Pases'!$F5,"PASE") -> 115 | K5: =IFERROR(VLOOKUP('Ventas Pases'!$J5,'Comisiones HEROIC'!$E$1:$F$6,2,0),"") -> Haiit Hotel | L5: =IF('Ventas Pases'!$D5="Red HEROIC",IFERROR(VLOOKUP('Ventas Pases'!$G5,'Comisiones HEROIC'!$A$1:$B$11,2,0),15),IF('Ventas Pases'!$D5="Red HEROIC",15,0)) -> 0 | M5: =IF(pases[[#This Row],[Días Visita]]<7,0,IF(pases[[#This Row],[Días Visita]]<9,1,IF(pases[[#This Row],[Días Visita]]="Ilimitados",0,2))) -> 1 | N5: =IF(AND('Ventas Pases'!$A5="Fuera de Temporada",'Ventas Pases'!$B5=2019,pases[[#This Row],[Modo de Compra]]="Paquete"),30,0) -> 0 | O5: =-SUMIF(lift[Número de pase],pases[[#This Row],[Numero de Pase]],lift[Costo]) -> 0
A6: Temporada Regular | B6: 2019 | C6: 43429 | D6: Red HEROIC | E6: 43492 | F6: 3 | G6: Montaña Panadero | H6: WSP-0005 | I6: 420 | J6: =IFERROR('Ventas Pases'!$I6/'Ventas Pases'!$F6,"PASE") -> 140 | K6: =IFERROR(VLOOKUP('Ventas Pases'!$J6,'Comisiones HEROIC'!$E$1:$F$6,2,0),"") | L6: =IF('Ventas Pases'!$D6="Red HEROIC",IFERROR(VLOOKUP('Ventas Pases'!$G6,'Comisiones HEROIC'!$A$1:$B$11,2,0),15),IF('Ventas Pases'!$D6="Red HEROIC",15,0)) -> 15 | M6: =IF(pases[[#This Row],[Días Visita]]<7,0,IF(pases[[#This Row],[Días Visita]]<9,1,IF(pases[[#This Row],[Días Visita]]="Ilimitados",0,2))) -> 0 | N6: =IF(AND('Ventas Pases'!$A6="Fuera de Temporada",'Ventas Pases'!$B6=2019,pases[[#This Row],[Modo de Compra]]="Paquete"),30,0) -> 0 | O6: =-SUMIF(lift[Número de pase],pases[[#This Row],[Numero de Pase]],lift[Costo]) -> 0
A7: Fuera de Temporada | B7: 2018 | C7: 43270 | D7: En Línea | E7: 42833 | F7: 2 | G7: Valle Silbador | H7: WSP-0006 | I7: 240 | J7: =IFERROR('Ventas Pases'!$I7/'Ventas Pases'!$F7,"PASE") -> 120 | K7: =IFERROR(VLOOKUP('Ventas Pases'!$J7,'Comisiones HEROIC'!$E$1:$F$6,2,0),"") | L7: =IF('Ventas Pases'!$D7="Red HEROIC",IFERROR(VLOOKUP('Ventas Pases'!$G7,'Comisiones HEROIC'!$A$1:$B$11,2,0),15),IF('Ventas Pases'!$D7="Red HEROIC",15,0)) -> 0 | M7: =IF(pases[[#This Row],[Días Visita]]<7,0,IF(pases[[#This Row],[Días Visita]]<9,1,IF(pases[[#This Row],[Días Visita]]="Ilimitados",0,2))) -> 0 | N7: =IF(AND('Ventas Pases'!$A7="Fuera de Temporada",'Ventas Pases'!$B7=2019,pases[[#This Row],[Modo de Compra]]="Paquete"),30,0) -> 0 | O7: =-SUMIF(lift[Número de pase],pases[[#This Row],[Numero de Pase]],lift[Costo]) -> 0
A8: Temporada Regular | B8: 2018 | C8: 43439 | D8: Paquete | E8: 43148 | F8: 4 | G8: Valle Silbador | H8: WSP-0007 | I8: 300 | J8: =IFERROR('Ventas Pases'!$I8/'Ventas Pases'!$F8,"PASE") -> 75 | K8: =IFERROR(VLOOKUP('Ventas Pases'!$J8,'Comisiones HEROIC'!$E$1:$F$6,2,0),"") -> Ski Inn | L8: =IF('Ventas Pases'!$D8="Red HEROIC",IFERROR(VLOOKUP('Ventas Pases'!$G8,'Comisiones HEROIC'!$A$1:$B$11,2,0),15),IF('Ventas Pases'!$D8="Red HEROIC",15,0)) -> 0 | M8: =IF(pases[[#This Row],[Días Visita]]<7,0,IF(pases[[#This Row],[Días Visita]]<9,1,IF(pases[[#This Row],[Días Visita]]="Ilimitados",0,2))) -> 0 | N8: =IF(AND('Ventas Pases'!$A8="Fuera de Temporada",'Ventas Pases'!$B8=2019,pases[[#This Row],[Modo de Compra]]="Paquete"),30,0) -> 0 | O8: =-SUMIF(lift[Número de pase],pases[[#This Row],[Numero de Pase]],lift[Costo]) -> 0
A9: Fuera de Temporada | B9: 2019 | C9: 43227 | D9: Paquete | E9: 43233 | F9: 6 | G9: Valle Silbador | H9: WSP-0008 | I9: 660 | J9: =IFERROR('Ventas Pases'!$I9/'Ventas Pases'!$F9,"PASE") -> 110 | K9: =IFERROR(VLOOKUP('Ventas Pases'!$J9,'Comisiones HEROIC'!$E$1:$F$6,2,0),"") -> Elton Hotel | L9: =IF('Ventas Pases'!$D9="Red HEROIC",IFERROR(VLOOKUP('Ventas Pases'!$G9,'Comisiones HEROIC'!$A$1:$B$11,2,0),15),IF('Ventas Pases'!$D9="Red HEROIC",15,0)) -> 0 | M9: =IF(pases[[#This Row],[Días Visita]]<7,0,IF(pases[[#This Row],[Días Visita]]<9,1,IF(pases[[#This Row],[Días Visita]]="Ilimitados",0,2))) -> 0 | N9: =IF(AND('Ventas Pases'!$A9="Fuera de Temporada",'Ventas Pases'!$B9=2019,pases[[#This Row],[Modo de Compra]]="Paquete"),30,0) -> 30 | O9: =-SUMIF(lift[Número de pase],pases[[#This Row],[Numero de Pase]],lift[Costo]) -> 0
A10: Temporada Regular | B10: 2019 | C10: 43508 | D10: En Línea | E10: 43508 | F10: 4 | G10: Valle Silbador | H10: WSP-0009 | I10: 480 | J10: =IFERROR('Ventas Pases'!$I10/'Ventas Pases'!$F10,"PASE") -> 120 | K10: =IFERROR(VLOOKUP('Ventas Pases'!$J10,'Comisiones HEROIC'!$E$1:$F$6,2,0),"") | L10: =IF('Ventas Pases'!$D10="Red HEROIC",IFERROR(VLOOKUP('Ventas Pases'!$G10,'Comisiones HEROIC'!$A$1:$B$11,2,0),15),IF('Ventas Pases'!$D10="Red HEROIC",15,0)) -> 0 | M10: =IF(pases[[#This Row],[Días Visita]]<7,0,IF(pases[[#This Row],[Días Visita]]<9,1,IF(pases[[#This Row],[Días Visita]]="Ilimitados",0,2))) -> 0 | N10: =IF(AND('Ventas Pases'!$A10="Fuera de Temporada",'Ventas Pases'!$B10=2019,pases[[#This Row],[Modo de Compra]]="Paquete"),30,0) -> 0 | O10: =-SUMIF(lift[Número de pase],pases[[#This Row],[Numero de Pase]],lift[Costo]) -> 0
A11: Temporada Regular | B11: 2019 | C11: 43547 | D11: En Línea | E11: 43419 | F11: Ilimitados | G11: Valle Silbador | H11: WSP-0010 | I11: 1950 | J11: =IFERROR('Ventas Pases'!$I11/'Ventas Pases'!$F11,"PASE") -> PASE | K11: =IFERROR(VLOOKUP('Ventas Pases'!$J11,'Comisiones HEROIC'!$E$1:$F$6,2,0),"") | L11: =IF('Ventas Pases'!$D11="Red HEROIC",IFERROR(VLOOKUP('Ventas Pases'!$G11,'Comisiones HEROIC'!$A$1:$B$11,2,0),15),IF('Ventas Pases'!$D11="Red HEROIC",15,0)) -> 0 | M11: =IF(pases[[#This Row],[Días Visita]]<7,0,IF(pases[[#This Row],[Días Visita]]<9,1,IF(pases[[#This Row],[Días Visita]]="Ilimitados",0,2))) -> 0 | N11: =IF(AND('Ventas Pases'!$A11="Fuera de Temporada",'Ventas Pases'!$B11=2019,pases[[#This Row],[Modo de Compra]]="Paquete"),30,0) -> 0 | O11: =-SUMIF(lift[Número de pase],pases[[#This Row],[Numero de Pase]],lift[Costo]) -> -368
A12: Temporada Regular | B12: 2019 | C12: 43494 | D12: En Línea | E12: 43504 | F12: 5 | G12: Valle Silbador | H12: WSP-0011 | I12: 600 | J12: =IFERROR('Ventas Pases'!$I12/'Ventas Pases'!$F12,"PASE") -> 120 | K12: =IFERROR(VLOOKUP('Ventas Pases'!$J12,'Comisiones HEROIC'!$E$1:$F$6,2,0),"") | L12: =IF('Ventas Pases'!$D12="Red HEROIC",IFERROR(VLOOKUP('Ventas Pases'!$G12,'Comisiones HEROIC'!$A$1:$B$11,2,0),15),IF('Ventas Pases'!$D12="Red HEROIC",15,0)) -> 0 | M12: =IF(pases[[#This Row],[Días Visita]]<7,0,IF(pases[[#This Row],[Días Visita]]<9,1,IF(pases[[#This Row],[Días Visita]]="Ilimitados",0,2))) -> 0 | N12: =IF(AND('Ventas Pases'!$A12="Fuera de Temporada",'Ventas Pases'!$B12=2019,pases[[#This Row],[Modo de Compra]]="Paquete"),30,0) -> 0 | O12: =-SUMIF(lift[Número de pase],pases[[#This Row],[Numero de Pase]],lift[Costo]) -> 0
A13: Fuera de Temporada | B13: 2019 | C13: 43262 | D13: Red HEROIC | E13: 43225 | F13: 9 | G13: Ski Comanche | H13: WSP-0012 | I13: 1260 | J13: =IFERROR('Ventas Pases'!$I13/'Ventas Pases'!$F13,"PASE") -> 140 | K13: =IFERROR(VLOOKUP('Ventas Pases'!$J13,'Comisiones HEROIC'!$E$1:$F$6,2,0),"") | L13: =IF('Ventas Pases'!$D13="Red HEROIC",IFERROR(VLOOKUP('Ventas Pases'!$G13,'Comisiones HEROIC'!$A$1:$B$11,2,0),15),IF('Ventas Pases'!$D13="Red HEROIC",15,0)) -> 15 | M13: =IF(pases[[#This Row],[Días Visita]]<7,0,IF(pases[[#This Row],[Días Visita]]<9,1,IF(pases[[#This Row],[Días Visita]]="Ilimitados",0,2))) -> 2 | N13: =IF(AND('Ventas Pases'!$A13="Fuera de Temporada",'Ventas Pases'!$B13=2019,pases[[#This Row],[Modo de Compra]]="Paquete"),30,0) -> 0 | O13: =-SUMIF(lift[Número de pase],pases[[#This Row],[Numero de Pase]],lift[Costo]) -> 0
A14: Temporada Regular | B14: 2018 | C14: 43428 | D14: Paquete | E14: 43061 | F14: 3 | G14: Valle Silbador | H14: WSP-0013 | I14: 330 | J14: =IFERROR('Ventas Pases'!$I14/'Ventas Pases'!$F14,"PASE") -> 110 | K14: =IFERROR(VLOOKUP('Ventas Pases'!$J14,'Comisiones HEROIC'!$E$1:$F$6,2,0),"") -> Elton Hotel | L14: =IF('Ventas Pases'!$D14="Red HEROIC",IFERROR(VLOOKUP('Ventas Pases'!$G14,'Comisiones HEROIC'!$A$1:$B$11,2,0),15),IF('Ventas Pases'!$D14="Red HEROIC",15,0)) -> 0 | M14: =IF(pases[[#This Row],[Días Visita]]<7,0,IF(pases[[#This Row],[Días Visita]]<9,1,IF(pases[[#This Row],[Días Visita]]="Ilimitados",0,2))) -> 0 | N14: =IF(AND('Ventas Pases'!$A14="Fuera de Temporada",'Ventas Pases'!$B14=2019,pases[[#This Row],[Modo de Compra]]="Paquete"),30,0) -> 0 | O14: =-SUMIF(lift[Número de pase],pases[[#This Row],[Numero de Pase]],lift[Costo]) -> 0
A15: Temporada Regular | B15: 2019 | C15: 43504 | D15: Paquete | E15: 43501 | F15: 9 | G15: Valle Silbador | H15: WSP-0014 | I15: 945 | J15: =IFERROR('Ventas Pases'!$I15/'Ventas Pases'!$F15,"PASE") -> 105 | K15: =IFERROR(VLOOKUP('Ventas Pases'!$J15,'Comisiones HEROIC'!$E$1:$F$6,2,0),"") -> OI Hotels | L15: =IF('Ventas Pases'!$D15="Red HEROIC",IFERROR(VLOOKUP('Ventas Pases'!$G15,'Comisiones HEROIC'!$A$1:$B$11,2,0),15),IF('Ventas Pases'!$D15="Red HEROIC",15,0)) -> 0 | M15: =IF(pases[[#This Row],[Días Visita]]<7,0,IF(pases[[#This Row],[Días Visita]]<9,1,IF(pases[[#This Row],[Días Visita]]="Ilimitados",0,2))) -> 2 | N15: =IF(AND('Ventas Pases'!$A15="Fuera de Temporada",'Ventas Pases'!$B15=2019,pases[[#This Row],[Modo de Compra]]="Paquete"),30,0) -> 0 | O15: =-SUMIF(lift[Número de pase],pases[[#This Row],[Numero de Pase]],lift[Costo]) -> 0
A16: Temporada Regular | B16: 2018 | C16: 43158 | D16: Paquete | E16: 43171 | F16: 3 | G16: Valle Silbador | H16: WSP-0015 | I16: 330 | J16: =IFERROR('Ventas Pases'!$I16/'Ventas Pases'!$F16,"PASE") -> 110 | K16: =IFERROR(VLOOKUP('Ventas Pases'!$J16,'Comisiones HEROIC'!$E$1:$F$6,2,0),"") -> Elton Hotel | L16: =IF('Ventas Pases'!$D16="Red HEROIC",IFERROR(VLOOKUP('Ventas Pases'!$G16,'Comisiones HEROIC'!$A$1:$B$11,2,0),15),IF('Ventas Pases'!$D16="Red HEROIC",15,0)) -> 0 | M16: =IF(pases[[#This Row],[Días Visita]]<7,0,IF(pases[[#This Row],[Días Visita]]<9,1,IF(pases[[#This Row],[Días Visita]]="Ilimitados",0,2))) -> 0 | N16: =IF(AND('Ventas Pases'!$A16="Fuera de Temporada",'Ventas Pases'!$B16=2019,pases[[#This Row],[Modo de Compra]]="Paquete"),30,0) -> 0 | O16: =-SUMIF(lift[Número de pase],pases[[#This Row],[Numero de Pase]],lift[Costo]) -> 0
A17: Temporada Regular | B17: 2018 | C17: 43435 | D17: En Línea | E17: 43144 | F17: 5 | G17: Valle Silbador | H17: WSP-0016 | I17: 600 | J17: =IFERROR('Ventas Pases'!$I17/'Ventas Pases'!$F17,"PASE") -> 120 | K17: =IFERROR(VLOOKUP('Ventas Pases'!$J17,'Comisiones HEROIC'!$E$1:$F$6,2,0),"") | L17: =IF('Ventas Pases'!$D17="Red HEROIC",IFERROR(VLOOKUP('Ventas Pases'!$G17,'Comisiones HEROIC'!$A$1:$B$11,2,0),15),IF('Ventas Pases'!$D17="Red HEROIC",15,0)) -> 0 | M17: =IF(pases[[#This Row],[Días Visita]]<7,0,IF(pases[[#This Row],[Días Visita]]<9,1,IF(pases[[#This Row],[Días Visita]]="Ilimitados",0,2))) -> 0 | N17: =IF(AND('Ventas Pases'!$A17="Fuera de Temporada",'Ventas Pases'!$B17=2019,pases[[#This Row],[Modo de Compra]]="Paquete"),30,0) -> 0 | O17: =-SUMIF(lift[Número de pase],pases[[#This Row],[Numero de Pase]],lift[Costo]) -> 0
A18: Temporada Regular | B18: 2019 | C18: 43476 | D18: Red HEROIC | E18: 43483 | F18: 3 | G18: Cresta Velo | H18: WSP-0017 | I18: 420 | J18: =IFERROR('Ventas Pases'!$I18/'Ventas Pases'!$F18,"PASE") -> 140 | K18: =IFERROR(VLOOKUP('Ventas Pases'!$J18,'Comisiones HEROIC'!$E$1:$F$6,2,0),"") | L18: =IF('Ventas Pases'!$D18="Red HEROIC",IFERROR(VLOOKUP('Ventas Pases'!$G18,'Comisiones HEROIC'!$A$1:$B$11,2,0),15),IF('Ventas Pases'!$D18="Red HEROIC",15,0)) -> 15 | M18: =IF(pases[[#This Row],[Días Visita]]<7,0,IF(pases[[#This Row],[Días Visita]]<9,1,IF(pases[[#This Row],[Días Visita]]="Ilimitados",0,2))) -> 0 | N18: =IF(AND('Ventas Pases'!$A18="Fuera de Temporada",'Ventas Pases'!$B18=2019,pases[[#This Row],[Modo de Compra]]="Paquete"),30,0) -> 0 | O18: =-SUMIF(lift[Número de pase],pases[[#This Row],[Numero de Pase]],lift[Costo]) -> 0
A19: Temporada Regular | B19: 2018 | C19: 43439 | D19: Red HEROIC | E19: 43078 | F19: 5 | G19: Monte Japón | H19: WSP-0018 | I19: 700 | J19: =IFERROR('Ventas Pases'!$I19/'Ventas Pases'!$F19,"PASE") -> 140 | K19: =IFERROR(VLOOKUP('Ventas Pases'!$J19,'Comisiones HEROIC'!$E$1:$F$6,2,0),"") | L19: =IF('Ventas Pases'!$D19="Red HEROIC",IFERROR(VLOOKUP('Ventas Pases'!$G19,'Comisiones HEROIC'!$A$1:$B$11,2,0),15),IF('Ventas Pases'!$D19="Red HEROIC",15,0)) -> 16 | M19: =IF(pases[[#This Row],[Días Visita]]<7,0,IF(pases[[#This Row],[Días Visita]]<9,1,IF(pases[[#This Row],[Días Visita]]="Ilimitados",0,2))) -> 0 | N19: =IF(AND('Ventas Pases'!$A19="Fuera de Temporada",'Ventas Pases'!$B19=2019,pases[[#This Row],[Modo de Compra]]="Paquete"),30,0) -> 0 | O19: =-SUMIF(lift[Número de pase],pases[[#This Row],[Numero de Pase]],lift[Costo]) -> 0
A20: Temporada Regular | B20: 2018 | C20: 43462 | D20: En Línea | E20: 43113 | F20: 3 | G20: Valle Silbador | H20: WSP-0019 | I20: 360 | J20: =IFERROR('Ventas Pases'!$I20/'Ventas Pases'!$F20,"PASE") -> 120 | K20: =IFERROR(VLOOKUP('Ventas Pases'!$J20,'Comisiones HEROIC'!$E$1:$F$6,2,0),"") | L20: =IF('Ventas Pases'!$D20="Red HEROIC",IFERROR(VLOOKUP('Ventas Pases'!$G20,'Comisiones HEROIC'!$A$1:$B$11,2,0),15),IF('Ventas Pases'!$D20="Red HEROIC",15,0)) -> 0 | M20: =IF(pases[[#This Row],[Días Visita]]<7,0,IF(pases[[#This Row],[Días Visita]]<9,1,IF(pases[[#This Row],[Días Visita]]="Ilimitados",0,2))) -> 0 | N20: =IF(AND('Ventas Pases'!$A20="Fuera de Temporada",'Ventas Pases'!$B20=2019,pases[[#This Row],[Modo de Compra]]="Paquete"),30,0) -> 0 | O20: =-SUMIF(lift[Número de pase],pases[[#This Row],[Numero de Pase]],lift[Costo]) -> 0
A21: Fuera de Temporada | B21: 2018 | C21: 43376 | D21: En Línea | E21: 43054 | F21: Ilimitados | G21: Valle Silbador | H21: WSP-0020 | I21: 1950 | J21: =IFERROR('Ventas Pases'!$I21/'Ventas Pases'!$F21,"PASE") -> PASE | K21: =IFERROR(VLOOKUP('Ventas Pases'!$J21,'Comisiones HEROIC'!$E$1:$F$6,2,0),"") | L21: =IF('Ventas Pases'!$D21="Red HEROIC",IFERROR(VLOOKUP('Ventas Pases'!$G21,'Comisiones HEROIC'!$A$1:$B$11,2,0),15),IF('Ventas Pases'!$D21="Red HEROIC",15,0)) -> 0 | M21: =IF(pases[[#This Row],[Días Visita]]<7,0,IF(pases[[#This Row],[Días Visita]]<9,1,IF(pases[[#This Row],[Días Visita]]="Ilimitados",0,2))) -> 0 | N21: =IF(AND('Ventas Pases'!$A21="Fuera de Temporada",'Ventas Pases'!$B21=2019,pases[[#This Row],[Modo de Compra]]="Paquete"),30,0) -> 0 | O21: =-SUMIF(lift[Número de pase],pases[[#This Row],[Numero de Pase]],lift[Costo]) -> -276
A22: Temporada Regular | B22: 2019 | C22: 43511 | D22: En Línea | E22: 43419 | F22: Ilimitados | G22: Valle Silbador | H22: WSP-0021 | I22: 1950 | J22: =IFERROR('Ventas Pases'!$I22/'Ventas Pases'!$F22,"PASE") -> PASE | K22: =IFERROR(VLOOKUP('Ventas Pases'!$J22,'Comisiones HEROIC'!$E$1:$F$6,2,0),"") | L22: =IF('Ventas Pases'!$D22="Red HEROIC",IFERROR(VLOOKUP('Ventas Pases'!$G22,'Comisiones HEROIC'!$A$1:$B$11,2,0),15),IF('Ventas Pases'!$D22="Red HEROIC",15,0)) -> 0 | M22: =IF(pases[[#This Row],[Días Visita]]<7,0,IF(pases[[#This Row],[Días Visita]]<9,1,IF(pases[[#This Row],[Días Visita]]="Ilimitados",0,2))) -> 0 | N22: =IF(AND('Ventas Pases'!$A22="Fuera de Temporada",'Ventas Pases'!$B22=2019,pases[[#This Row],[Modo de Compra]]="Paquete"),30,0) -> 0 | O22: =-SUMIF(lift[Número de pase],pases[[#This Row],[Numero de Pase]],lift[Costo]) -> -920
A23: Fuera de Temporada | B23: 2019 | C23: 43318 | D23: Paquete | E23: 43202 | F23: 6 | G23: Valle Silbador | H23: WSP-0022 | I23: 660 | J23: =IFERROR('Ventas Pases'!$I23/'Ventas Pases'!$F23,"PASE") -> 110 | K23: =IFERROR(VLOOKUP('Ventas Pases'!$J23,'Comisiones HEROIC'!$E$1:$F$6,2,0),"") -> Elton Hotel | L23: =IF('Ventas Pases'!$D23="Red HEROIC",IFERROR(VLOOKUP('Ventas Pases'!$G23,'Comisiones HEROIC'!$A$1:$B$11,2,0),15),IF('Ventas Pases'!$D23="Red HEROIC",15,0)) -> 0 | M23: =IF(pases[[#This Row],[Días Visita]]<7,0,IF(pases[[#This Row],[Días Visita]]<9,1,IF(pases[[#This Row],[Días Visita]]="Ilimitados",0,2))) -> 0 | N23: =IF(AND('Ventas Pases'!$A23="Fuera de Temporada",'Ventas Pases'!$B23=2019,pases[[#This Row],[Modo de Compra]]="Paquete"),30,0) -> 30 | O23: =-SUMIF(lift[Número de pase],pases[[#This Row],[Numero de Pase]],lift[Costo]) -> 0
A24: Temporada Regular | B24: 2019 | C24: 43421 | D24: Red HEROIC | E24: 43433 | F24: 6 | G24: Cresta Velo | H24: WSP-0023 | I24: 840 | J24: =IFERROR('Ventas Pases'!$I24/'Ventas Pases'!$F24,"PASE") -> 140 | K24: =IFERROR(VLOOKUP('Ventas Pases'!$J24,'Comisiones HEROIC'!$E$1:$F$6,2,0),"") | L24: =IF('Ventas Pases'!$D24="Red HEROIC",IFERROR(VLOOKUP('Ventas Pases'!$G24,'Comisiones HEROIC'!$A$1:$B$11,2,0),15),IF('Ventas Pases'!$D24="Red HEROIC",15,0)) -> 15 | M24: =IF(pases[[#This Row],[Días Visita]]<7,0,IF(pases[[#This Row],[Días Visita]]<9,1,IF(pases[[#This Row],[Días Visita]]="Ilimitados",0,2))) -> 0 | N24: =IF(AND('Ventas Pases'!$A24="Fuera de Temporada",'Ventas Pases'!$B24=2019,pases[[#This Row],[Modo de Compra]]="Paquete"),30,0) -> 0 | O24: =-SUMIF(lift[Número de pase],pases[[#This Row],[Numero de Pase]],lift[Costo]) -> 0
A25: Temporada Regular | B25: 2018 | C25: 43142 | D25: En Línea | E25: 43054 | F25: Ilimitados | G25: Valle Silbador | H25: WSP-0024 | I25: 1950 | J25: =IFERROR('Ventas Pases'!$I25/'Ventas Pases'!$F25,"PASE") -> PASE | K25: =IFERROR(VLOOKUP('Ventas Pases'!$J25,'Comisiones HEROIC'!$E$1:$F$6,2,0),"") | L25: =IF('Ventas Pases'!$D25="Red HEROIC",IFERROR(VLOOKUP('Ventas Pases'!$G25,'Comisiones HEROIC'!$A$1:$B$11,2,0),15),IF('Ventas Pases'!$D25="Red HEROIC",15,0)) -> 0 | M25: =IF(pases[[#This Row],[Días Visita]]<7,0,IF(pases[[#This Row],[Días Visita]]<9,1,IF(pases[[#This Row],[Días Visita]]="Ilimitados",0,2))) -> 0 | N25: =IF(AND('Ventas Pases'!$A25="Fuera de Temporada",'Ventas Pases'!$B25=2019,pases[[#This Row],[Modo de Compra]]="Paquete"),30,0) -> 0 | O25: =-SUMIF(lift[Número de pase],pases[[#This Row],[Numero de Pase]],lift[Costo]) -> -828
A26: Temporada Regular | B26: 2018 | C26: 43457 | D26: Paquete | E26: 43125 | F26: 9 | G26: Valle Silbador | H26: WSP-0025 | I26: 900 | J26: =IFERROR('Ventas Pases'!$I26/'Ventas Pases'!$F26,"PASE") -> 100 | K26: =IFERROR(VLOOKUP('Ventas Pases'!$J26,'Comisiones HEROIC'!$E$1:$F$6,2,0),"") -> Ridossan Hotel | L26: =IF('Ventas Pases'!$D26="Red HEROIC",IFERROR(VLOOKUP('Ventas Pases'!$G26,'Comisiones HEROIC'!$A$1:$B$11,2,0),15),IF('Ventas Pases'!$D26="Red HEROIC",15,0)) -> 0 | M26: =IF(pases[[#This Row],[Días Visita]]<7,0,IF(pases[[#This Row],[Días Visita]]<9,1,IF(pases[[#This Row],[Días Visita]]="Ilimitados",0,2))) -> 2 | N26: =IF(AND('Ventas Pases'!$A26="Fuera de Temporada",'Ventas Pases'!$B26=2019,pases[[#This Row],[Modo de Compra]]="Paquete"),30,0) -> 0 | O26: =-SUMIF(lift[Número de pase],pases[[#This Row],[Numero de Pase]],lift[Costo]) -> 0
A27: Fuera de Temporada | B27: 2018 | C27: 43331 | D27: En Línea | E27: 43054 | F27: Ilimitados | G27: Valle Silbador | H27: WSP-0026 | I27: 1950 | J27: =IFERROR('Ventas Pases'!$I27/'Ventas Pases'!$F27,"PASE") -> PASE | K27: =IFERROR(VLOOKUP('Ventas Pases'!$J27,'Comisiones HEROIC'!$E$1:$F$6,2,0),"") | L27: =IF('Ventas Pases'!$D27="Red HEROIC",IFERROR(VLOOKUP('Ventas Pases'!$G27,'Comisiones HEROIC'!$A$1:$B$11,2,0),15),IF('Ventas Pases'!$D27="Red HEROIC",15,0)) -> 0 | M27: =IF(pases[[#This Row],[Días Visita]]<7,0,IF(pases[[#This Row],[Días Visita]]<9,1,IF(pases[[#This Row],[Días Visita]]="Ilimitados",0,2))) -> 0 | N27: =IF(AND('Ventas Pases'!$A27="Fuera de Temporada",'Ventas Pases'!$B27=2019,pases[[#This Row],[Modo de Compra]]="Paquete"),30,0) -> 0 | O27: =-SUMIF(lift[Número de pase],pases[[#This Row],[Numero de Pase]],lift[Costo]) -> -368
A28: Temporada Regular | B28: 2018 | C28: 43449 | D28: En Línea | E28: 43054 | F28: Ilimitados | G28: Valle Silbador | H28: WSP-0027 | I28: 1950 | J28: =IFERROR('Ventas Pases'!$I28/'Ventas Pases'!$F28,"PASE") -> PASE | K28: =IFERROR(VLOOKUP('Ventas Pases'!$J28,'Comisiones HEROIC'!$E$1:$F$6,2,0),"") | L28: =IF('Ventas Pases'!$D28="Red HEROIC",IFERROR(VLOOKUP('Ventas Pases'!$G28,'Comisiones HEROIC'!$A$1:$B$11,2,0),15),IF('Ventas Pases'!$D28="Red HEROIC",15,0)) -> 0 | M28: =IF(pases[[#This Row],[Días Visita]]<7,0,IF(pases[[#This Row],[Días Visita]]<9,1,IF(pases[[#This Row],[Días Visita]]="Ilimitados",0,2))) -> 0 | N28: =IF(AND('Ventas Pases'!$A28="Fuera de Temporada",'Ventas Pases'!$B28=2019,pases[[#This Row],[Modo de Compra]]="Paquete"),30,0) -> 0 | O28: =-SUMIF(lift[Número de pase],pases[[#This Row],[Numero de Pase]],lift[Costo]) -> -460
A29: Fuera de Temporada | B29: 2019 | C29: 43384 | D29: Paquete | E29: 43244 | F29: 6 | G29: Valle Silbador | H29: WSP-0028 | I29: 660 | J29: =IFERROR('Ventas Pases'!$I29/'Ventas Pases'!$F29,"PASE") -> 110 | K29: =IFERROR(VLOOKUP('Ventas Pases'!$J29,'Comisiones HEROIC'!$E$1:$F$6,2,0),"") -> Elton Hotel | L29: =IF('Ventas Pases'!$D29="Red HEROIC",IFERROR(VLOOKUP('Ventas Pases'!$G29,'Comisiones HEROIC'!$A$1:$B$11,2,0),15),IF('Ventas Pases'!$D29="Red HEROIC",15,0)) -> 0 | M29: =IF(pases[[#This Row],[Días Visita]]<7,0,IF(pases[[#This Row],[Días Visita]]<9,1,IF(pases[[#This Row],[Días Visita]]="Ilimitados",0,2))) -> 0 | N29: =IF(AND('Ventas Pases'!$A29="Fuera de Temporada",'Ventas Pases'!$B29=2019,pases[[#This Row],[Modo de Compra]]="Paquete"),30,0) -> 30 | O29: =-SUMIF(lift[Número de pase],pases[[#This Row],[Numero de Pase]],lift[Costo]) -> 0
A30: Temporada Regular | B30: 2019 | C30: 43428 | D30: En Línea | E30: 43419 | F30: Ilimitados | G30: Valle Silbador | H30: WSP-0029 | I30: 1950 | J30: =IFERROR('Ventas Pases'!$I30/'Ventas Pases'!$F30,"PASE") -> PASE | K30: =IFERROR(VLOOKUP('Ventas Pases'!$J30,'Comisiones HEROIC'!$E$1:$F$6,2,0),"") | L30: =IF('Ventas Pases'!$D30="Red HEROIC",IFERROR(VLOOKUP('Ventas Pases'!$G30,'Comisiones HEROIC'!$A$1:$B$11,2,0),15),IF('Ventas Pases'!$D30="Red HEROIC",15,0)) -> 0 | M30: =IF(pases[[#This Row],[Días Visita]]<7,0,IF(pases[[#This Row],[Días Visita]]<9,1,IF(pases[[#This Row],[Días Visita]]="Ilimitados",0,2))) -> 0 | N30: =IF(AND('Ventas Pases'!$A30="Fuera de Temporada",'Ventas Pases'!$B30=2019,pases[[#This Row],[Modo de Compra]]="Paquete"),30,0) -> 0 | O30: =-SUMIF(lift[Número de pase],pases[[#This Row],[Numero de Pase]],lift[Costo]) -> -460
A31: Temporada Regular | B31: 2019 | C31: 43452 | D31: En Línea | E31: 43449 | F31: 7 | G31: Valle Silbador | H31: WSP-0030 | I31: 840 | J31: =IFERROR('Ventas Pases'!$I31/'Ventas Pases'!$F31,"PASE") -> 120 | K31: =IFERROR(VLOOKUP('Ventas Pases'!$J31,'Comisiones HEROIC'!$E$1:$F$6,2,0),"") | L31: =IF('Ventas Pases'!$D31="Red HEROIC",IFERROR(VLOOKUP('Ventas Pases'!$G31,'Comisiones HEROIC'!$A$1:$B$11,2,0),15),IF('Ventas Pases'!$D31="Red HEROIC",15,0)) -> 0 | M31: =IF(pases[[#This Row],[Días Visita]]<7,0,IF(pases[[#This Row],[Días Visita]]<9,1,IF(pases[[#This Row],[Días Visita]]="Ilimitados",0,2))) -> 1 | N31: =IF(AND('Ventas Pases'!$A31="Fuera de Temporada",'Ventas Pases'!$B31=2019,pases[[#This Row],[Modo de Compra]]="Paquete"),30,0) -> 0 | O31: =-SUMIF(lift[Número de pase],pases[[#This Row],[Numero de Pase]],lift[Costo]) -> 0
A32: Temporada Regular | B32: 2019 | C32: 43517 | D32: Paquete | E32: 43541 | F32: 6 | G32: Valle Silbador | H32: WSP-0031 | I32: 660 | J32: =IFERROR('Ventas Pases'!$I32/'Ventas Pases'!$F32,"PASE") -> 110 | K32: =IFERROR(VLOOKUP('Ventas Pases'!$J32,'Comisiones HEROIC'!$E$1:$F$6,2,0),"") -> Elton Hotel | L32: =IF('Ventas Pases'!$D32="Red HEROIC",IFERROR(VLOOKUP('Ventas Pases'!$G32,'Comisiones HEROIC'!$A$1:$B$11,2,0),15),IF('Ventas Pases'!$D32="Red HEROIC",15,0)) -> 0 | M32: =IF(pases[[#This Row],[Días Visita]]<7,0,IF(pases[[#This Row],[Días Visita]]<9,1,IF(pases[[#This Row],[Días Visita]]="Ilimitados",0,2))) -> 0 | N32: =IF(AND('Ventas Pases'!$A32="Fuera de Temporada",'Ventas Pases'!$B32=2019,pases[[#This Row],[Modo de Compra]]="Paquete"),30,0) -> 0 | O32: =-SUMIF(lift[Número de pase],pases[[#This Row],[Numero de Pase]],lift[Costo]) -> 0
A33: Temporada Regular | B33: 2019 | C33: 43449 | D33: Paquete | E33: 43532 | F33: 4 | G33: Valle Silbador | H33: WSP-0032 | I33: 400 | J33: =IFERROR('Ventas Pases'!$I33/'Ventas Pases'!$F33,"PASE") -> 100 | K33: =IFERROR(VLOOKUP('Ventas Pases'!$J33,'Comisiones HEROIC'!$E$1:$F$6,2,0),"") -> Ridossan Hotel | L33: =IF('Ventas Pases'!$D33="Red HEROIC",IFERROR(VLOOKUP('Ventas Pases'!$G33,'Comisiones HEROIC'!$A$1:$B$11,2,0),15),IF('Ventas Pases'!$D33="Red HEROIC",15,0)) -> 0 | M33: =IF(pases[[#This Row],[Días Visita]]<7,0,IF(pases[[#This Row],[Días Visita]]<9,1,IF(pases[[#This Row],[Días Visita]]="Ilimitados",0,2))) -> 0 | N33: =IF(AND('Ventas Pases'!$A33="Fuera de Temporada",'Ventas Pases'!$B33=2019,pases[[#This Row],[Modo de Compra]]="Paquete"),30,0) -> 0 | O33: =-SUMIF(lift[Número de pase],pases[[#This Row],[Numero de Pase]],lift[Costo]) -> 0
A34: Fuera de Temporada | B34: 2019 | C34: 43268 | D34: En Línea | E34: 43266 | F34: 9 | G34: Valle Silbador | H34: WSP-0033 | I34: 1080 | J34: =IFERROR('Ventas Pases'!$I34/'Ventas Pases'!$F34,"PASE") -> 120 | K34: =IFERROR(VLOOKUP('Ventas Pases'!$J34,'Comisiones HEROIC'!$E$1:$F$6,2,0),"") | L34: =IF('Ventas Pases'!$D34="Red HEROIC",IFERROR(VLOOKUP('Ventas Pases'!$G34,'Comisiones HEROIC'!$A$1:$B$11,2,0),15),IF('Ventas Pases'!$D34="Red HEROIC",15,0)) -> 0 | M34: =IF(pases[[#This Row],[Días Visita]]<7,0,IF(pases[[#This Row],[Días Visita]]<9,1,IF(pases[[#This Row],[Días Visita]]="Ilimitados",0,2))) -> 2 | N34: =IF(AND('Ventas Pases'!$A34="Fuera de Temporada",'Ventas Pases'!$B34=2019,pases[[#This Row],[Modo de Compra]]="Paquete"),30,0) -> 0 | O34: =-SUMIF(lift[Número de pase],pases[[#This Row],[Numero de Pase]],lift[Costo]) -> 0
A35: Fuera de Temporada | B35: 2018 | C35: 43298 | D35: Red HEROIC | E35: 42851 | F35: 4 | G35: Cresta Velo | H35: WSP-0034 | I35: 560 | J35: =IFERROR('Ventas Pases'!$I35/'Ventas Pases'!$F35,"PASE") -> 140 | K35: =IFERROR(VLOOKUP('Ventas Pases'!$J35,'Comisiones HEROIC'!$E$1:$F$6,2,0),"") | L35: =IF('Ventas Pases'!$D35="Red HEROIC",IFERROR(VLOOKUP('Ventas Pases'!$G35,'Comisiones HEROIC'!$A$1:$B$11,2,0),15),IF('Ventas Pases'!$D35="Red HEROIC",15,0)) -> 15 | M35: =IF(pases[[#This Row],[Días Visita]]<7,0,IF(pases[[#This Row],[Días Visita]]<9,1,IF(pases[[#This Row],[Días Visita]]="Ilimitados",0,2))) -> 0 | N35: =IF(AND('Ventas Pases'!$A35="Fuera de Temporada",'Ventas Pases'!$B35=2019,pases[[#This Row],[Modo de Compra]]="Paquete"),30,0) -> 0 | O35: =-SUMIF(lift[Número de pase],pases[[#This Row],[Numero de Pase]],lift[Costo]) -> 0
A36: Temporada Regular | B36: 2018 | C36: 43107 | D36: Red HEROIC | E36: 43121 | F36: 5 | G36: Puente Roto | H36: WSP-0035 | I36: 700 | J36: =IFERROR('Ventas Pases'!$I36/'Ventas Pases'!$F36,"PASE") -> 140 | K36: =IFERROR(VLOOKUP('Ventas Pases'!$J36,'Comisiones HEROIC'!$E$1:$F$6,2,0),"") | L36: =IF('Ventas Pases'!$D36="Red HEROIC",IFERROR(VLOOKUP('Ventas Pases'!$G36,'Comisiones HEROIC'!$A$1:$B$11,2,0),15),IF('Ventas Pases'!$D36="Red HEROIC",15,0)) -> 12 | M36: =IF(pases[[#This Row],[Días Visita]]<7,0,IF(pases[[#This Row],[Días Visita]]<9,1,IF(pases[[#This Row],[Días Visita]]="Ilimitados",0,2))) -> 0 | N36: =IF(AND('Ventas Pases'!$A36="Fuera de Temporada",'Ventas Pases'!$B36=2019,pases[[#This Row],[Modo de Compra]]="Paquete"),30,0) -> 0 | O36: =-SUMIF(lift[Número de pase],pases[[#This Row],[Numero de Pase]],lift[Costo]) -> 0
A37: Temporada Regular | B37: 2019 | C37: 43554 | D37: En Línea | E37: 43546 | F37: 7 | G37: Valle Silbador | H37: WSP-0036 | I37: 840 | J37: =IFERROR('Ventas Pases'!$I37/'Ventas Pases'!$F37,"PASE") -> 120 | K37: =IFERROR(VLOOKUP('Ventas Pases'!$J37,'Comisiones HEROIC'!$E$1:$F$6,2,0),"") | L37: =IF('Ventas Pases'!$D37="Red HEROIC",IFERROR(VLOOKUP('Ventas Pases'!$G37,'Comisiones HEROIC'!$A$1:$B$11,2,0),15),IF('Ventas Pases'!$D37="Red HEROIC",15,0)) -> 0 | M37: =IF(pases[[#This Row],[Días Visita]]<7,0,IF(pases[[#This Row],[Días Visita]]<9,1,IF(pases[[#This Row],[Días Visita]]="Ilimitados",0,2))) -> 1 | N37: =IF(AND('Ventas Pases'!$A37="Fuera de Temporada",'Ventas Pases'!$B37=2019,pases[[#This Row],[Modo de Compra]]="Paquete"),30,0) -> 0 | O37: =-SUMIF(lift[Número de pase],pases[[#This Row],[Numero de Pase]],lift[Costo]) -> 0
A38: Temporada Regular | B38: 2019 | C38: 43479 | D38: Paquete | E38: 43525 | F38: 8 | G38: Valle Silbador | H38: WSP-0037 | I38: 880 | J38: =IFERROR('Ventas Pases'!$I38/'Ventas Pases'!$F38,"PASE") -> 110 | K38: =IFERROR(VLOOKUP('Ventas Pases'!$J38,'Comisiones HEROIC'!$E$1:$F$6,2,0),"") -> Elton Hotel | L38: =IF('Ventas Pases'!$D38="Red HEROIC",IFERROR(VLOOKUP('Ventas Pases'!$G38,'Comisiones HEROIC'!$A$1:$B$11,2,0),15),IF('Ventas Pases'!$D38="Red HEROIC",15,0)) -> 0 | M38: =IF(pases[[#This Row],[Días Visita]]<7,0,IF(pases[[#This Row],[Días Visita]]<9,1,IF(pases[[#This Row],[Días Visita]]="Ilimitados",0,2))) -> 1 | N38: =IF(AND('Ventas Pases'!$A38="Fuera de Temporada",'Ventas Pases'!$B38=2019,pases[[#This Row],[Modo de Compra]]="Paquete"),30,0) -> 0 | O38: =-SUMIF(lift[Número de pase],pases[[#This Row],[Numero de Pase]],lift[Costo]) -> 0
A39: Temporada Regular | B39: 2019 | C39: 43555 | D39: En Línea | E39: 43419 | F39: Ilimitados | G39: Valle Silbador | H39: WSP-0038 | I39: 1950 | J39: =IFERROR('Ventas Pases'!$I39/'Ventas Pases'!$F39,"PASE") -> PASE | K39: =IFERROR(VLOOKUP('Ventas Pases'!$J39,'Comisiones HEROIC'!$E$1:$F$6,2,0),"") | L39: =IF('Ventas Pases'!$D39="Red HEROIC",IFERROR(VLOOKUP('Ventas Pases'!$G39,'Comisiones HEROIC'!$A$1:$B$11,2,0),15),IF('Ventas Pases'!$D39="Red HEROIC",15,0)) -> 0 | M39: =IF(pases[[#This Row],[Días Visita]]<7,0,IF(pases[[#This Row],[Días Visita]]<9,1,IF(pases[[#This Row],[Días Visita]]="Ilimitados",0,2))) -> 0 | N39: =IF(AND('Ventas Pases'!$A39="Fuera de Temporada",'Ventas Pases'!$B39=2019,pases[[#This Row],[Modo de Compra]]="Paquete"),30,0) -> 0 | O39: =-SUMIF(lift[Número de pase],pases[[#This Row],[Numero de Pase]],lift[Costo]) -> -552
A40: Temporada Regular | B40: 2018 | C40: 43120 | D40: Red HEROIC | E40: 43173 | F40: 1 | G40: Puente Roto | H40: WSP-0039 | I40: 140 | J40: =IFERROR('Ventas Pases'!$I40/'Ventas Pases'!$F40,"PASE") -> 140 | K40: =IFERROR(VLOOKUP('Ventas Pases'!$J40,'Comisiones HEROIC'!$E$1:$F$6,2,0),"") | L40: =IF('Ventas Pases'!$D40="Red HEROIC",IFERROR(VLOOKUP('Ventas Pases'!$G40,'Comisiones HEROIC'!$A$1:$B$11,2,0),15),IF('Ventas Pases'!$D40="Red HEROIC",15,0)) -> 12 | M40: =IF(pases[[#This Row],[Días Visita]]<7,0,IF(pases[[#This Row],[Días Visita]]<9,1,IF(pases[[#This Row],[Días Visita]]="Ilimitados",0,2))) -> 0 | N40: =IF(AND('Ventas Pases'!$A40="Fuera de Temporada",'Ventas Pases'!$B40=2019,pases[[#This Row],[Modo de Compra]]="Paquete"),30,0) -> 0 | O40: =-SUMIF(lift[Número de pase],pases[[#This Row],[Numero de Pase]],lift[Costo]) -> 0
A41: Temporada Regular | B41: 2018 | C41: 43103 | D41: Red HEROIC | E41: 43166 | F41: 8 | G41: Ski Comanche | H41: WSP-0040 | I41: 1120 | J41: =IFERROR('Ventas Pases'!$I41/'Ventas Pases'!$F41,"PASE") -> 140 | K41: =IFERROR(VLOOKUP('Ventas Pases'!$J41,'Comisiones HEROIC'!$E$1:$F$6,2,0),"") | L41: =IF('Ventas Pases'!$D41="Red HEROIC",IFERROR(VLOOKUP('Ventas Pases'!$G41,'Comisiones HEROIC'!$A$1:$B$11,2,0),15),IF('Ventas Pases'!$D41="Red HEROIC",15,0)) -> 15 | M41: =IF(pases[[#This Row],[Días Visita]]<7,0,IF(pases[[#This Row],[Días Visita]]<9,1,IF(pases[[#This Row],[Días Visita]]="Ilimitados",0,2))) -> 1 | N41: =IF(AND('Ventas Pases'!$A41="Fuera de Temporada",'Ventas Pases'!$B41=2019,pases[[#This Row],[Modo de Compra]]="Paquete"),30,0) -> 0 | O41: =-SUMIF(lift[Número de pase],pases[[#This Row],[Numero de Pase]],lift[Costo]) -> 0
A42: Temporada Regular | B42: 2018 | C42: 43433 | D42: Red HEROIC | E42: 43094 | F42: 7 | G42: Cresta Velo | H42: WSP-0041 | I42: 980 | J42: =IFERROR('Ventas Pases'!$I42/'Ventas Pases'!$F42,"PASE") -> 140 | K42: =IFERROR(VLOOKUP('Ventas Pases'!$J42,'Comisiones HEROIC'!$E$1:$F$6,2,0),"") | L42: =IF('Ventas Pases'!$D42="Red HEROIC",IFERROR(VLOOKUP('Ventas Pases'!$G42,'Comisiones HEROIC'!$A$1:$B$11,2,0),15),IF('Ventas Pases'!$D42="Red HEROIC",15,0)) -> 15 | M42: =IF(pases[[#This Row],[Días Visita]]<7,0,IF(pases[[#This Row],[Días Visita]]<9,1,IF(pases[[#This Row],[Días Visita]]="Ilimitados",0,2))) -> 1 | N42: =IF(AND('Ventas Pases'!$A42="Fuera de Temporada",'Ventas Pases'!$B42=2019,pases[[#This Row],[Modo de Compra]]="Paquete"),30,0) -> 0 | O42: =-SUMIF(lift[Número de pase],pases[[#This Row],[Numero de Pase]],lift[Costo]) -> 0
A43: Fuera de Temporada | B43: 2018 | C43: 43400 | D43: Físico | E43: 42849 | F43: 6 | G43: Valle Silbador | H43: WSP-0042 | I43: 720 | J43: =IFERROR('Ventas Pases'!$I43/'Ventas Pases'!$F43,"PASE") -> 120 | K43: =IFERROR(VLOOKUP('Ventas Pases'!$J43,'Comisiones HEROIC'!$E$1:$F$6,2,0),"") | L43: =IF('Ventas Pases'!$D43="Red HEROIC",IFERROR(VLOOKUP('Ventas Pases'!$G43,'Comisiones HEROIC'!$A$1:$B$11,2,0),15),IF('Ventas Pases'!$D43="Red HEROIC",15,0)) -> 0 | M43: =IF(pases[[#This Row],[Días Visita]]<7,0,IF(pases[[#This Row],[Días Visita]]<9,1,IF(pases[[#This Row],[Días Visita]]="Ilimitados",0,2))) -> 0 | N43: =IF(AND('Ventas Pases'!$A43="Fuera de Temporada",'Ventas Pases'!$B43=2019,pases[[#This Row],[Modo de Compra]]="Paquete"),30,0) -> 0 | O43: =-SUMIF(lift[Número de pase],pases[[#This Row],[Numero de Pase]],lift[Costo]) -> 0
A44: Temporada Regular | B44: 2019 | C44: 43460 | D44: Paquete | E44: 43529 | F44: 7 | G44: Valle Silbador | H44: WSP-0043 | I44: 700 | J44: =IFERROR('Ventas Pases'!$I44/'Ventas Pases'!$F44,"PASE") -> 100 | K44: =IFERROR(VLOOKUP('Ventas Pases'!$J44,'Comisiones HEROIC'!$E$1:$F$6,2,0),"") -> Ridossan Hotel | L44: =IF('Ventas Pases'!$D44="Red HEROIC",IFERROR(VLOOKUP('Ventas Pases'!$G44,'Comisiones HEROIC'!$A$1:$B$11,2,0),15),IF('Ventas Pases'!$D44="Red HEROIC",15,0)) -> 0 | M44: =IF(pases[[#This Row],[Días Visita]]<7,0,IF(pases[[#This Row],[Días Visita]]<9,1,IF(pases[[#This Row],[Días Visita]]="Ilimitados",0,2))) -> 1 | N44: =IF(AND('Ventas Pases'!$A44="Fuera de Temporada",'Ventas Pases'!$B44=2019,pases[[#This Row],[Modo de Compra]]="Paquete"),30,0) -> 0 | O44: =-SUMIF(lift[Número de pase],pases[[#This Row],[Numero de Pase]],lift[Costo]) -> 0
A45: Fuera de Temporada | B45: 2019 | C45: 43200 | D45: Paquete | E45: 43308 | F45: 1 | G45: Valle Silbador | H45: WSP-0044 | I45: 110 | J45: =IFERROR('Ventas Pases'!$I45/'Ventas Pases'!$F45,"PASE") -> 110 | K45: =IFERROR(VLOOKUP('Ventas Pases'!$J45,'Comisiones HEROIC'!$E$1:$F$6,2,0),"") -> Elton Hotel | L45: =IF('Ventas Pases'!$D45="Red HEROIC",IFERROR(VLOOKUP('Ventas Pases'!$G45,'Comisiones HEROIC'!$A$1:$B$11,2,0),15),IF('Ventas Pases'!$D45="Red HEROIC",15,0)) -> 0 | M45: =IF(pases[[#This Row],[Días Visita]]<7,0,IF(pases[[#This Row],[Días Visita]]<9,1,IF(pases[[#This Row],[Días Visita]]="Ilimitados",0,2))) -> 0 | N45: =IF(AND('Ventas Pases'!$A45="Fuera de Temporada",'Ventas Pases'!$B45=2019,pases[[#This Row],[Modo de Compra]]="Paquete"),30,0) -> 30 | O45: =-SUMIF(lift[Número de pase],pases[[#This Row],[Numero de Pase]],lift[Costo]) -> 0
A46: Temporada Regular | B46: 2019 | C46: 43554 | D46: Paquete | E46: 43545 | F46: 3 | G46: Valle Silbador | H46: WSP-0045 | I46: 315 | J46: =IFERROR('Ventas Pases'!$I46/'Ventas Pases'!$F46,"PASE") -> 105 | K46: =IFERROR(VLOOKUP('Ventas Pases'!$J46,'Comisiones HEROIC'!$E$1:$F$6,2,0),"") -> OI Hotels | L46: =IF('Ventas Pases'!$D46="Red HEROIC",IFERROR(VLOOKUP('Ventas Pases'!$G46,'Comisiones HEROIC'!$A$1:$B$11,2,0),15),IF('Ventas Pases'!$D46="Red HEROIC",15,0)) -> 0 | M46: =IF(pases[[#This Row],[Días Visita]]<7,0,IF(pases[[#This Row],[Días Visita]]<9,1,IF(pases[[#This Row],[Días Visita]]="Ilimitados",0,2))) -> 0 | N46: =IF(AND('Ventas Pases'!$A46="Fuera de Temporada",'Ventas Pases'!$B46=2019,pases[[#This Row],[Modo de Compra]]="Paquete"),30,0) -> 0 | O46: =-SUMIF(lift[Número de pase],pases[[#This Row],[Numero de Pase]],lift[Costo]) -> 0
A47: Temporada Regular | B47: 2019 | C47: 43466 | D47: Red HEROIC | E47: 43465 | F47: 5 | G47: Monte Japón | H47: WSP-0046 | I47: 700 | J47: =IFERROR('Ventas Pases'!$I47/'Ventas Pases'!$F47,"PASE") -> 140 | K47: =IFERROR(VLOOKUP('Ventas Pases'!$J47,'Comisiones HEROIC'!$E$1:$F$6,2,0),"") | L47: =IF('Ventas Pases'!$D47="Red HEROIC",IFERROR(VLOOKUP('Ventas Pases'!$G47,'Comisiones HEROIC'!$A$1:$B$11,2,0),15),IF('Ventas Pases'!$D47="Red HEROIC",15,0)) -> 16 | M47: =IF(pases[[#This Row],[Días Visita]]<7,0,IF(pases[[#This Row],[Días Visita]]<9,1,IF(pases[[#This Row],[Días Visita]]="Ilimitados",0,2))) -> 0 | N47: =IF(AND('Ventas Pases'!$A47="Fuera de Temporada",'Ventas Pases'!$B47=2019,pases[[#This Row],[Modo de Compra]]="Paquete"),30,0) -> 0 | O47: =-SUMIF(lift[Número de pase],pases[[#This Row],[Numero de Pase]],lift[Costo]) -> 0
A48: Temporada Regular | B48: 2018 | C48: 43141 | D48: En Línea | E48: 43181 | F48: 7 | G48: Valle Silbador | H48: WSP-0047 | I48: 840 | J48: =IFERROR('Ventas Pases'!$I48/'Ventas Pases'!$F48,"PASE") -> 120 | K48: =IFERROR(VLOOKUP('Ventas Pases'!$J48,'Comisiones HEROIC'!$E$1:$F$6,2,0),"") | L48: =IF('Ventas Pases'!$D48="Red HEROIC",IFERROR(VLOOKUP('Ventas Pases'!$G48,'Comisiones HEROIC'!$A$1:$B$11,2,0),15),IF('Ventas Pases'!$D48="Red HEROIC",15,0)) -> 0 | M48: =IF(pases[[#This Row],[Días Visita]]<7,0,IF(pases[[#This Row],[Días Visita]]<9,1,IF(pases[[#This Row],[Días Visita]]="Ilimitados",0,2))) -> 1 | N48: =IF(AND('Ventas Pases'!$A48="Fuera de Temporada",'Ventas Pases'!$B48=2019,pases[[#This Row],[Modo de Compra]]="Paquete"),30,0) -> 0 | O48: =-SUMIF(lift[Número de pase],pases[[#This Row],[Numero de Pase]],lift[Costo]) -> 0
A49: Temporada Regular | B49: 2019 | C49: 43521 | D49: En Línea | E49: 43521 | F49: 3 | G49: Valle Silbador | H49: WSP-0048 | I49: 360 | J49: =IFERROR('Ventas Pases'!$I49/'Ventas Pases'!$F49,"PASE") -> 120 | K49: =IFERROR(VLOOKUP('Ventas Pases'!$J49,'Comisiones HEROIC'!$E$1:$F$6,2,0),"") | L49: =IF('Ventas Pases'!$D49="Red HEROIC",IFERROR(VLOOKUP('Ventas Pases'!$G49,'Comisiones HEROIC'!$A$1:$B$11,2,0),15),IF('Ventas Pases'!$D49="Red HEROIC",15,0)) -> 0 | M49: =IF(pases[[#This Row],[Días Visita]]<7,0,IF(pases[[#This Row],[Días Visita]]<9,1,IF(pases[[#This Row],[Días Visita]]="Ilimitados",0,2))) -> 0 | N49: =IF(AND('Ventas Pases'!$A49="Fuera de Temporada",'Ventas Pases'!$B49=2019,pases[[#This Row],[Modo de Compra]]="Paquete"),30,0) -> 0 | O49: =-SUMIF(lift[Número de pase],pases[[#This Row],[Numero de Pase]],lift[Costo]) -> 0
A50: Temporada Regular | B50: 2019 | C50: 43423 | D50: Red HEROIC | E50: 43476 | F50: 1 | G50: Montaña Panadero | H50: WSP-0049 | I50: 140 | J50: =IFERROR('Ventas Pases'!$I50/'Ventas Pases'!$F50,"PASE") -> 140 | K50: =IFERROR(VLOOKUP('Ventas Pases'!$J50,'Comisiones HEROIC'!$E$1:$F$6,2,0),"") | L50: =IF('Ventas Pases'!$D50="Red HEROIC",IFERROR(VLOOKUP('Ventas Pases'!$G50,'Comisiones HEROIC'!$A$1:$B$11,2,0),15),IF('Ventas Pases'!$D50="Red HEROIC",15,0)) -> 15 | M50: =IF(pases[[#This Row],[Días Visita]]<7,0,IF(pases[[#This Row],[Días Visita]]<9,1,IF(pases[[#This Row],[Días Visita]]="Ilimitados",0,2))) -> 0 | N50: =IF(AND('Ventas Pases'!$A50="Fuera de Temporada",'Ventas Pases'!$B50=2019,pases[[#This Row],[Modo de Compra]]="Paquete"),30,0) -> 0 | O50: =-SUMIF(lift[Número de pase],pases[[#This Row],[Numero de Pase]],lift[Costo]) -> 0
A51: Temporada Regular | B51: 2019 | C51: 43456 | D51: En Línea | E51: 43476 | F51: 9 | G51: Valle Silbador | H51: WSP-0050 | I51: 1080 | J51: =IFERROR('Ventas Pases'!$I51/'Ventas Pases'!$F51,"PASE") -> 120 | K51: =IFERROR(VLOOKUP('Ventas Pases'!$J51,'Comisiones HEROIC'!$E$1:$F$6,2,0),"") | L51: =IF('Ventas Pases'!$D51="Red HEROIC",IFERROR(VLOOKUP('Ventas Pases'!$G51,'Comisiones HEROIC'!$A$1:$B$11,2,0),15),IF('Ventas Pases'!$D51="Red HEROIC",15,0)) -> 0 | M51: =IF(pases[[#This Row],[Días Visita]]<7,0,IF(pases[[#This Row],[Días Visita]]<9,1,IF(pases[[#This Row],[Días Visita]]="Ilimitados",0,2))) -> 2 | N51: =IF(AND('Ventas Pases'!$A51="Fuera de Temporada",'Ventas Pases'!$B51=2019,pases[[#This Row],[Modo de Compra]]="Paquete"),30,0) -> 0 | O51: =-SUMIF(lift[Número de pase],pases[[#This Row],[Numero de Pase]],lift[Costo]) -> 0
... A54: Temporada Regular | B54: 2019 | C54: 43508 | D54: En Línea | E54: 43544 | F54: 5 | G54: Valle Silbador | H54: WSP-0053 | I54: 600 | J54: =IFERROR('Ventas Pases'!$I54/'Ventas Pases'!$F54,"PASE") -> 120 | K54: =IFERROR(VLOOKUP('Ventas Pases'!$J54,'Comisiones HEROIC'!$E$1:$F$6,2,0),"") | L54: =IF('Ventas Pases'!$D54="Red HEROIC",IFERROR(VLOOKUP('Ventas Pases'!$G54,'Comisiones HEROIC'!$A$1:$B$11,2,0),15),IF('Ventas Pases'!$D54="Red HEROIC",15,0)) -> 0 | M54: =IF(pases[[#This Row],[Días Visita]]<7,0,IF(pases[[#This Row],[Días Visita]]<9,1,IF(pases[[#This Row],[Días Visita]]="Ilimitados",0,2))) -> 0 | N54: =IF(AND('Ventas Pases'!$A54="Fuera de Temporada",'Ventas Pases'!$B54=2019,pases[[#This Row],[Modo de Compra]]="Paquete"),30,0) -> 0 | O54: =-SUMIF(lift[Número de pase],pases[[#This Row],[Numero de Pase]],lift[Costo]) -> 0
A55: Temporada Regular | B55: 2019 | C55: 43553 | D55: En Línea | E55: 43419 | F55: Ilimitados | G55: Valle Silbador | H55: WSP-0054 | I55: 1950 | J55: =IFERROR('Ventas Pases'!$I55/'Ventas Pases'!$F55,"PASE") -> PASE | K55: =IFERROR(VLOOKUP('Ventas Pases'!$J55,'Comisiones HEROIC'!$E$1:$F$6,2,0),"") | L55: =IF('Ventas Pases'!$D55="Red HEROIC",IFERROR(VLOOKUP('Ventas Pases'!$G55,'Comisiones HEROIC'!$A$1:$B$11,2,0),15),IF('Ventas Pases'!$D55="Red HEROIC",15,0)) -> 0 | M55: =IF(pases[[#This Row],[Días Visita]]<7,0,IF(pases[[#This Row],[Días Visita]]<9,1,IF(pases[[#This Row],[Días Visita]]="Ilimitados",0,2))) -> 0 | N55: =IF(AND('Ventas Pases'!$A55="Fuera de Temporada",'Ventas Pases'!$B55=2019,pases[[#This Row],[Modo de Compra]]="Paquete"),30,0) -> 0 | O55: =-SUMIF(lift[Número de pase],pases[[#This Row],[Numero de Pase]],lift[Costo]) -> -552
A56: Temporada Regular | B56: 2019 | C56: 43419 | D56: En Línea | E56: 43441 | F56: 5 | G56: Valle Silbador | H56: WSP-0055 | I56: 600 | J56: =IFERROR('Ventas Pases'!$I56/'Ventas Pases'!$F56,"PASE") -> 120 | K56: =IFERROR(VLOOKUP('Ventas Pases'!$J56,'Comisiones HEROIC'!$E$1:$F$6,2,0),"") | L56: =IF('Ventas Pases'!$D56="Red HEROIC",IFERROR(VLOOKUP('Ventas Pases'!$G56,'Comisiones HEROIC'!$A$1:$B$11,2,0),15),IF('Ventas Pases'!$D56="Red HEROIC",15,0)) -> 0 | M56: =IF(pases[[#This Row],[Días Visita]]<7,0,IF(pases[[#This Row],[Días Visita]]<9,1,IF(pases[[#This Row],[Días Visita]]="Ilimitados",0,2))) -> 0 | N56: =IF(AND('Ventas Pases'!$A56="Fuera de Temporada",'Ventas Pases'!$B56=2019,pases[[#This Row],[Modo de Compra]]="Paquete"),30,0) -> 0 | O56: =-SUMIF(lift[Número de pase],pases[[#This Row],[Numero de Pase]],lift[Costo]) -> 0
A57: Fuera de Temporada | B57: 2018 | C57: 43282 | D57: En Línea | E57: 42909 | F57: 5 | G57: Valle Silbador | H57: WSP-0056 | I57: 600 | J57: =IFERROR('Ventas Pases'!$I57/'Ventas Pases'!$F57,"PASE") -> 120 | K57: =IFERROR(VLOOKUP('Ventas Pases'!$J57,'Comisiones HEROIC'!$E$1:$F$6,2,0),"") | L57: =IF('Ventas Pases'!$D57="Red HEROIC",IFERROR(VLOOKUP('Ventas Pases'!$G57,'Comisiones HEROIC'!$A$1:$B$11,2,0),15),IF('Ventas Pases'!$D57="Red HEROIC",15,0)) -> 0 | M57: =IF(pases[[#This Row],[Días Visita]]<7,0,IF(pases[[#This Row],[Días Visita]]<9,1,IF(pases[[#This Row],[Días Visita]]="Ilimitados",0,2))) -> 0 | N57: =IF(AND('Ventas Pases'!$A57="Fuera de Temporada",'Ventas Pases'!$B57=2019,pases[[#This Row],[Modo de Compra]]="Paquete"),30,0) -> 0 | O57: =-SUMIF(lift[Número de pase],pases[[#This Row],[Numero de Pase]],lift[Costo]) -> 0
A58: Temporada Regular | B58: 2019 | C58: 43469 | D58: Paquete | E58: 43518 | F58: 3 | G58: Valle Silbador | H58: WSP-0057 | I58: 225 | J58: =IFERROR('Ventas Pases'!$I58/'Ventas Pases'!$F58,"PASE") -> 75 | K58: =IFERROR(VLOOKUP('Ventas Pases'!$J58,'Comisiones HEROIC'!$E$1:$F$6,2,0),"") -> Ski Inn | L58: =IF('Ventas Pases'!$D58="Red HEROIC",IFERROR(VLOOKUP('Ventas Pases'!$G58,'Comisiones HEROIC'!$A$1:$B$11,2,0),15),IF('Ventas Pases'!$D58="Red HEROIC",15,0)) -> 0 | M58: =IF(pases[[#This Row],[Días Visita]]<7,0,IF(pases[[#This Row],[Días Visita]]<9,1,IF(pases[[#This Row],[Días Visita]]="Ilimitados",0,2))) -> 0 | N58: =IF(AND('Ventas Pases'!$A58="Fuera de Temporada",'Ventas Pases'!$B58=2019,pases[[#This Row],[Modo de Compra]]="Paquete"),30,0) -> 0 | O58: =-SUMIF(lift[Número de pase],pases[[#This Row],[Numero de Pase]],lift[Costo]) -> 0
A59: Fuera de Temporada | B59: 2018 | C59: 43355 | D59: En Línea | E59: 43054 | F59: Ilimitados | G59: Valle Silbador | H59: WSP-0058 | I59: 1950 | J59: =IFERROR('Ventas Pases'!$I59/'Ventas Pases'!$F59,"PASE") -> PASE | K59: =IFERROR(VLOOKUP('Ventas Pases'!$J59,'Comisiones HEROIC'!$E$1:$F$6,2,0),"") | L59: =IF('Ventas Pases'!$D59="Red HEROIC",IFERROR(VLOOKUP('Ventas Pases'!$G59,'Comisiones HEROIC'!$A$1:$B$11,2,0),15),IF('Ventas Pases'!$D59="Red HEROIC",15,0)) -> 0 | M59: =IF(pases[[#This Row],[Días Visita]]<7,0,IF(pases[[#This Row],[Días Visita]]<9,1,IF(pases[[#This Row],[Días Visita]]="Ilimitados",0,2))) -> 0 | N59: =IF(AND('Ventas Pases'!$A59="Fuera de Temporada",'Ventas Pases'!$B59=2019,pases[[#This Row],[Modo de Compra]]="Paquete"),30,0) -> 0 | O59: =-SUMIF(lift[Número de pase],pases[[#This Row],[Numero de Pase]],lift[Costo]) -> -276
A60: Temporada Regular | B60: 2018 | C60: 43139 | D60: Red HEROIC | E60: 43134 | F60: 7 | G60: Cresta Velo | H60: WSP-0059 | I60: 980 | J60: =IFERROR('Ventas Pases'!$I60/'Ventas Pases'!$F60,"PASE") -> 140 | K60: =IFERROR(VLOOKUP('Ventas Pases'!$J60,'Comisiones HEROIC'!$E$1:$F$6,2,0),"") | L60: =IF('Ventas Pases'!$D60="Red HEROIC",IFERROR(VLOOKUP('Ventas Pases'!$G60,'Comisiones HEROIC'!$A$1:$B$11,2,0),15),IF('Ventas Pases'!$D60="Red HEROIC",15,0)) -> 15 | M60: =IF(pases[[#This Row],[Días Visita]]<7,0,IF(pases[[#This Row],[Días Visita]]<9,1,IF(pases[[#This Row],[Días Visita]]="Ilimitados",0,2))) -> 1 | N60: =IF(AND('Ventas Pases'!$A60="Fuera de Temporada",'Ventas Pases'!$B60=2019,pases[[#This Row],[Modo de Compra]]="Paquete"),30,0) -> 0 | O60: =-SUMIF(lift[Número de pase],pases[[#This Row],[Numero de Pase]],lift[Costo]) -> 0
A61: Temporada Regular | B61: 2018 | C61: 43421 | D61: En Línea | E61: 43084 | F61: 6 | G61: Valle Silbador | H61: WSP-0060 | I61: 720 | J61: =IFERROR('Ventas Pases'!$I61/'Ventas Pases'!$F61,"PASE") -> 120 | K61: =IFERROR(VLOOKUP('Ventas Pases'!$J61,'Comisiones HEROIC'!$E$1:$F$6,2,0),"") | L61: =IF('Ventas Pases'!$D61="Red HEROIC",IFERROR(VLOOKUP('Ventas Pases'!$G61,'Comisiones HEROIC'!$A$1:$B$11,2,0),15),IF('Ventas Pases'!$D61="Red HEROIC",15,0)) -> 0 | M61: =IF(pases[[#This Row],[Días Visita]]<7,0,IF(pases[[#This Row],[Días Visita]]<9,1,IF(pases[[#This Row],[Días Visita]]="Ilimitados",0,2))) -> 0 | N61: =IF(AND('Ventas Pases'!$A61="Fuera de Temporada",'Ventas Pases'!$B61=2019,pases[[#This Row],[Modo de Compra]]="Paquete"),30,0) -> 0 | O61: =-SUMIF(lift[Número de pase],pases[[#This Row],[Numero de Pase]],lift[Costo]) -> 0
A62: Temporada Regular | B62: 2018 | C62: 43138 | D62: Red HEROIC | E62: 43174 | F62: 1 | G62: Ski Comanche | H62: WSP-0061 | I62: 140 | J62: =IFERROR('Ventas Pases'!$I62/'Ventas Pases'!$F62,"PASE") -> 140 | K62: =IFERROR(VLOOKUP('Ventas Pases'!$J62,'Comisiones HEROIC'!$E$1:$F$6,2,0),"") | L62: =IF('Ventas Pases'!$D62="Red HEROIC",IFERROR(VLOOKUP('Ventas Pases'!$G62,'Comisiones HEROIC'!$A$1:$B$11,2,0),15),IF('Ventas Pases'!$D62="Red HEROIC",15,0)) -> 15 | M62: =IF(pases[[#This Row],[Días Visita]]<7,0,IF(pases[[#This Row],[Días Visita]]<9,1,IF(pases[[#This Row],[Días Visita]]="Ilimitados",0,2))) -> 0 | N62: =IF(AND('Ventas Pases'!$A62="Fuera de Temporada",'Ventas Pases'!$B62=2019,pases[[#This Row],[Modo de Compra]]="Paquete"),30,0) -> 0 | O62: =-SUMIF(lift[Número de pase],pases[[#This Row],[Numero de Pase]],lift[Costo]) -> 0
A63: Temporada Regular | B63: 2018 | C63: 43422 | D63: Red HEROIC | E63: 43119 | F63: 4 | G63: Puente Roto | H63: WSP-0062 | I63: 560 | J63: =IFERROR('Ventas Pases'!$I63/'Ventas Pases'!$F63,"PASE") -> 140 | K63: =IFERROR(VLOOKUP('Ventas Pases'!$J63,'Comisiones HEROIC'!$E$1:$F$6,2,0),"") | L63: =IF('Ventas Pases'!$D63="Red HEROIC",IFERROR(VLOOKUP('Ventas Pases'!$G63,'Comisiones HEROIC'!$A$1:$B$11,2,0),15),IF('Ventas Pases'!$D63="Red HEROIC",15,0)) -> 12 | M63: =IF(pases[[#This Row],[Días Visita]]<7,0,IF(pases[[#This Row],[Días Visita]]<9,1,IF(pases[[#This Row],[Días Visita]]="Ilimitados",0,2))) -> 0 | N63: =IF(AND('Ventas Pases'!$A63="Fuera de Temporada",'Ventas Pases'!$B63=2019,pases[[#This Row],[Modo de Compra]]="Paquete"),30,0) -> 0 | O63: =-SUMIF(lift[Número de pase],pases[[#This Row],[Numero de Pase]],lift[Costo]) -> 0
A64: Fuera de Temporada | B64: 2018 | C64: 43354 | D64: En Línea | E64: 42899 | F64: 7 | G64: Valle Silbador | H64: WSP-0063 | I64: 840 | J64: =IFERROR('Ventas Pases'!$I64/'Ventas Pases'!$F64,"PASE") -> 120 | K64: =IFERROR(VLOOKUP('Ventas Pases'!$J64,'Comisiones HEROIC'!$E$1:$F$6,2,0),"") | L64: =IF('Ventas Pases'!$D64="Red HEROIC",IFERROR(VLOOKUP('Ventas Pases'!$G64,'Comisiones HEROIC'!$A$1:$B$11,2,0),15),IF('Ventas Pases'!$D64="Red HEROIC",15,0)) -> 0 | M64: =IF(pases[[#This Row],[Días Visita]]<7,0,IF(pases[[#This Row],[Días Visita]]<9,1,IF(pases[[#This Row],[Días Visita]]="Ilimitados",0,2))) -> 1 | N64: =IF(AND('Ventas Pases'!$A64="Fuera de Temporada",'Ventas Pases'!$B64=2019,pases[[#This Row],[Modo de Compra]]="Paquete"),30,0) -> 0 | O64: =-SUMIF(lift[Número de pase],pases[[#This Row],[Numero de Pase]],lift[Costo]) -> 0
A65: Temporada Regular | B65: 2018 | C65: 43158 | D65: En Línea | E65: 43170 | F65: 7 | G65: Valle Silbador | H65: WSP-0064 | I65: 840 | J65: =IFERROR('Ventas Pases'!$I65/'Ventas Pases'!$F65,"PASE") -> 120 | K65: =IFERROR(VLOOKUP('Ventas Pases'!$J65,'Comisiones HEROIC'!$E$1:$F$6,2,0),"") | L65: =IF('Ventas Pases'!$D65="Red HEROIC",IFERROR(VLOOKUP('Ventas Pases'!$G65,'Comisiones HEROIC'!$A$1:$B$11,2,0),15),IF('Ventas Pases'!$D65="Red HEROIC",15,0)) -> 0 | M65: =IF(pases[[#This Row],[Días Visita]]<7,0,IF(pases[[#This Row],[Días Visita]]<9,1,IF(pases[[#This Row],[Días Visita]]="Ilimitados",0,2))) -> 1 | N65: =IF(AND('Ventas Pases'!$A65="Fuera de Temporada",'Ventas Pases'!$B65=2019,pases[[#This Row],[Modo de Compra]]="Paquete"),30,0) -> 0 | O65: =-SUMIF(lift[Número de pase],pases[[#This Row],[Numero de Pase]],lift[Costo]) -> 0
A66: Temporada Regular | B66: 2018 | C66: 43157 | D66: Paquete | E66: 43164 | F66: 6 | G66: Valle Silbador | H66: WSP-0065 | I66: 660 | J66: =IFERROR('Ventas Pases'!$I66/'Ventas Pases'!$F66,"PASE") -> 110 | K66: =IFERROR(VLOOKUP('Ventas Pases'!$J66,'Comisiones HEROIC'!$E$1:$F$6,2,0),"") -> Elton Hotel | L66: =IF('Ventas Pases'!$D66="Red HEROIC",IFERROR(VLOOKUP('Ventas Pases'!$G66,'Comisiones HEROIC'!$A$1:$B$11,2,0),15),IF('Ventas Pases'!$D66="Red HEROIC",15,0)) -> 0 | M66: =IF(pases[[#This Row],[Días Visita]]<7,0,IF(pases[[#This Row],[Días Visita]]<9,1,IF(pases[[#This Row],[Días Visita]]="Ilimitados",0,2))) -> 0 | N66: =IF(AND('Ventas Pases'!$A66="Fuera de Temporada",'Ventas Pases'!$B66=2019,pases[[#This Row],[Modo de Compra]]="Paquete"),30,0) -> 0 | O66: =-SUMIF(lift[Número de pase],pases[[#This Row],[Numero de Pase]],lift[Costo]) -> 0
A67: Temporada Regular | B67: 2019 | C67: 43514 | D67: En Línea | E67: 43419 | F67: Ilimitados | G67: Valle Silbador | H67: WSP-0066 | I67: 1950 | J67: =IFERROR('Ventas Pases'!$I67/'Ventas Pases'!$F67,"PASE") -> PASE | K67: =IFERROR(VLOOKUP('Ventas Pases'!$J67,'Comisiones HEROIC'!$E$1:$F$6,2,0),"") | L67: =IF('Ventas Pases'!$D67="Red HEROIC",IFERROR(VLOOKUP('Ventas Pases'!$G67,'Comisiones HEROIC'!$A$1:$B$11,2,0),15),IF('Ventas Pases'!$D67="Red HEROIC",15,0)) -> 0 | M67: =IF(pases[[#This Row],[Días Visita]]<7,0,IF(pases[[#This Row],[Días Visita]]<9,1,IF(pases[[#This Row],[Días Visita]]="Ilimitados",0,2))) -> 0 | N67: =IF(AND('Ventas Pases'!$A67="Fuera de Temporada",'Ventas Pases'!$B67=2019,pases[[#This Row],[Modo de Compra]]="Paquete"),30,0) -> 0 | O67: =-SUMIF(lift[Número de pase],pases[[#This Row],[Numero de Pase]],lift[Costo]) -> -276
A68: Fuera de Temporada | B68: 2018 | C68: 43209 | D68: En Línea | E68: 42829 | F68: 3 | G68: Valle Silbador | H68: WSP-0067 | I68: 360 | J68: =IFERROR('Ventas Pases'!$I68/'Ventas Pases'!$F68,"PASE") -> 120 | K68: =IFERROR(VLOOKUP('Ventas Pases'!$J68,'Comisiones HEROIC'!$E$1:$F$6,2,0),"") | L68: =IF('Ventas Pases'!$D68="Red HEROIC",IFERROR(VLOOKUP('Ventas Pases'!$G68,'Comisiones HEROIC'!$A$1:$B$11,2,0),15),IF('Ventas Pases'!$D68="Red HEROIC",15,0)) -> 0 | M68: =IF(pases[[#This Row],[Días Visita]]<7,0,IF(pases[[#This Row],[Días Visita]]<9,1,IF(pases[[#This Row],[Días Visita]]="Ilimitados",0,2))) -> 0 | N68: =IF(AND('Ventas Pases'!$A68="Fuera de Temporada",'Ventas Pases'!$B68=2019,pases[[#This Row],[Modo de Compra]]="Paquete"),30,0) -> 0 | O68: =-SUMIF(lift[Número de pase],pases[[#This Row],[Numero de Pase]],lift[Costo]) -> 0
A69: Temporada Regular | B69: 2019 | C69: 43530 | D69: En Línea | E69: 43545 | F69: 1 | G69: Valle Silbador | H69: WSP-0068 | I69: 120 | J69: =IFERROR('Ventas Pases'!$I69/'Ventas Pases'!$F69,"PASE") -> 120 | K69: =IFERROR(VLOOKUP('Ventas Pases'!$J69,'Comisiones HEROIC'!$E$1:$F$6,2,0),"") | L69: =IF('Ventas Pases'!$D69="Red HEROIC",IFERROR(VLOOKUP('Ventas Pases'!$G69,'Comisiones HEROIC'!$A$1:$B$11,2,0),15),IF('Ventas Pases'!$D69="Red HEROIC",15,0)) -> 0 | M69: =IF(pases[[#This Row],[Días Visita]]<7,0,IF(pases[[#This Row],[Días Visita]]<9,1,IF(pases[[#This Row],[Días Visita]]="Ilimitados",0,2))) -> 0 | N69: =IF(AND('Ventas Pases'!$A69="Fuera de Temporada",'Ventas Pases'!$B69=2019,pases[[#This Row],[Modo de Compra]]="Paquete"),30,0) -> 0 | O69: =-SUMIF(lift[Número de pase],pases[[#This Row],[Numero de Pase]],lift[Costo]) -> 0
A70: Fuera de Temporada | B70: 2018 | C70: 43287 | D70: En Línea | E70: 43054 | F70: Ilimitados | G70: Valle Silbador | H70: WSP-0069 | I70: 1950 | J70: =IFERROR('Ventas Pases'!$I70/'Ventas Pases'!$F70,"PASE") -> PASE | K70: =IFERROR(VLOOKUP('Ventas Pases'!$J70,'Comisiones HEROIC'!$E$1:$F$6,2,0),"") | L70: =IF('Ventas Pases'!$D70="Red HEROIC",IFERROR(VLOOKUP('Ventas Pases'!$G70,'Comisiones HEROIC'!$A$1:$B$11,2,0),15),IF('Ventas Pases'!$D70="Red HEROIC",15,0)) -> 0 | M70: =IF(pases[[#This Row],[Días Visita]]<7,0,IF(pases[[#This Row],[Días Visita]]<9,1,IF(pases[[#This Row],[Días Visita]]="Ilimitados",0,2))) -> 0 | N70: =IF(AND('Ventas Pases'!$A70="Fuera de Temporada",'Ventas Pases'!$B70=2019,pases[[#This Row],[Modo de Compra]]="Paquete"),30,0) -> 0 | O70: =-SUMIF(lift[Número de pase],pases[[#This Row],[Numero de Pase]],lift[Costo]) -> -460
A71: Temporada Regular | B71: 2018 | C71: 43140 | D71: En Línea | E71: 43161 | F71: 4 | G71: Valle Silbador | H71: WSP-0070 | I71: 480 | J71: =IFERROR('Ventas Pases'!$I71/'Ventas Pases'!$F71,"PASE") -> 120 | K71: =IFERROR(VLOOKUP('Ventas Pases'!$J71,'Comisiones HEROIC'!$E$1:$F$6,2,0),"") | L71: =IF('Ventas Pases'!$D71="Red HEROIC",IFERROR(VLOOKUP('Ventas Pases'!$G71,'Comisiones HEROIC'!$A$1:$B$11,2,0),15),IF('Ventas Pases'!$D71="Red HEROIC",15,0)) -> 0 | M71: =IF(pases[[#This Row],[Días Visita]]<7,0,IF(pases[[#This Row],[Días Visita]]<9,1,IF(pases[[#This Row],[Días Visita]]="Ilimitados",0,2))) -> 0 | N71: =IF(AND('Ventas Pases'!$A71="Fuera de Temporada",'Ventas Pases'!$B71=2019,pases[[#This Row],[Modo de Compra]]="Paquete"),30,0) -> 0 | O71: =-SUMIF(lift[Número de pase],pases[[#This Row],[Numero de Pase]],lift[Costo]) -> 0
A72: Fuera de Temporada | B72: 2018 | C72: 43309 | D72: En Línea | E72: 43054 | F72: Ilimitados | G72: Valle Silbador | H72: WSP-0071 | I72: 1950 | J72: =IFERROR('Ventas Pases'!$I72/'Ventas Pases'!$F72,"PASE") -> PASE | K72: =IFERROR(VLOOKUP('Ventas Pases'!$J72,'Comisiones HEROIC'!$E$1:$F$6,2,0),"") | L72: =IF('Ventas Pases'!$D72="Red HEROIC",IFERROR(VLOOKUP('Ventas Pases'!$G72,'Comisiones HEROIC'!$A$1:$B$11,2,0),15),IF('Ventas Pases'!$D72="Red HEROIC",15,0)) -> 0 | M72: =IF(pases[[#This Row],[Días Visita]]<7,0,IF(pases[[#This Row],[Días Visita]]<9,1,IF(pases[[#This Row],[Días Visita]]="Ilimitados",0,2))) -> 0 | N72: =IF(AND('Ventas Pases'!$A72="Fuera de Temporada",'Ventas Pases'!$B72=2019,pases[[#This Row],[Modo de Compra]]="Paquete"),30,0) -> 0 | O72: =-SUMIF(lift[Número de pase],pases[[#This Row],[Numero de Pase]],lift[Costo]) -> -92
A73: Temporada Regular | B73: 2018 | C73: 43450 | D73: Paquete | E73: 43174 | F73: 6 | G73: Valle Silbador | H73: WSP-0072 | I73: 660 | J73: =IFERROR('Ventas Pases'!$I73/'Ventas Pases'!$F73,"PASE") -> 110 | K73: =IFERROR(VLOOKUP('Ventas Pases'!$J73,'Comisiones HEROIC'!$E$1:$F$6,2,0),"") -> Elton Hotel | L73: =IF('Ventas Pases'!$D73="Red HEROIC",IFERROR(VLOOKUP('Ventas Pases'!$G73,'Comisiones HEROIC'!$A$1:$B$11,2,0),15),IF('Ventas Pases'!$D73="Red HEROIC",15,0)) -> 0 | M73: =IF(pases[[#This Row],[Días Visita]]<7,0,IF(pases[[#This Row],[Días Visita]]<9,1,IF(pases[[#This Row],[Días Visita]]="Ilimitados",0,2))) -> 0 | N73: =IF(AND('Ventas Pases'!$A73="Fuera de Temporada",'Ventas Pases'!$B73=2019,pases[[#This Row],[Modo de Compra]]="Paquete"),30,0) -> 0 | O73: =-SUMIF(lift[Número de pase],pases[[#This Row],[Numero de Pase]],lift[Costo]) -> 0
A74: Temporada Regular | B74: 2019 | C74: 43535 | D74: Físico | E74: 43539 | F74: 3 | G74: Valle Silbador | H74: WSP-0073 | I74: 360 | J74: =IFERROR('Ventas Pases'!$I74/'Ventas Pases'!$F74,"PASE") -> 120 | K74: =IFERROR(VLOOKUP('Ventas Pases'!$J74,'Comisiones HEROIC'!$E$1:$F$6,2,0),"") | L74: =IF('Ventas Pases'!$D74="Red HEROIC",IFERROR(VLOOKUP('Ventas Pases'!$G74,'Comisiones HEROIC'!$A$1:$B$11,2,0),15),IF('Ventas Pases'!$D74="Red HEROIC",15,0)) -> 0 | M74: =IF(pases[[#This Row],[Días Visita]]<7,0,IF(pases[[#This Row],[Días Visita]]<9,1,IF(pases[[#This Row],[Días Visita]]="Ilimitados",0,2))) -> 0 | N74: =IF(AND('Ventas Pases'!$A74="Fuera de Temporada",'Ventas Pases'!$B74=2019,pases[[#This Row],[Modo de Compra]]="Paquete"),30,0) -> 0 | O74: =-SUMIF(lift[Número de pase],pases[[#This Row],[Numero de Pase]],lift[Costo]) -> 0
A75: Temporada Regular | B75: 2019 | C75: 43501 | D75: Paquete | E75: 43512 | F75: 7 | G75: Valle Silbador | H75: WSP-0074 | I75: 770 | J75: =IFERROR('Ventas Pases'!$I75/'Ventas Pases'!$F75,"PASE") -> 110 | K75: =IFERROR(VLOOKUP('Ventas Pases'!$J75,'Comisiones HEROIC'!$E$1:$F$6,2,0),"") -> Elton Hotel | L75: =IF('Ventas Pases'!$D75="Red HEROIC",IFERROR(VLOOKUP('Ventas Pases'!$G75,'Comisiones HEROIC'!$A$1:$B$11,2,0),15),IF('Ventas Pases'!$D75="Red HEROIC",15,0)) -> 0 | M75: =IF(pases[[#This Row],[Días Visita]]<7,0,IF(pases[[#This Row],[Días Visita]]<9,1,IF(pases[[#This Row],[Días Visita]]="Ilimitados",0,2))) -> 1 | N75: =IF(AND('Ventas Pases'!$A75="Fuera de Temporada",'Ventas Pases'!$B75=2019,pases[[#This Row],[Modo de Compra]]="Paquete"),30,0) -> 0 | O75: =-SUMIF(lift[Número de pase],pases[[#This Row],[Numero de Pase]],lift[Costo]) -> 0
A76: Fuera de Temporada | B76: 2018 | C76: 43335 | D76: Red HEROIC | E76: 42872 | F76: 4 | G76: Ski Comanche | H76: WSP-0075 | I76: 560 | J76: =IFERROR('Ventas Pases'!$I76/'Ventas Pases'!$F76,"PASE") -> 140 | K76: =IFERROR(VLOOKUP('Ventas Pases'!$J76,'Comisiones HEROIC'!$E$1:$F$6,2,0),"") | L76: =IF('Ventas Pases'!$D76="Red HEROIC",IFERROR(VLOOKUP('Ventas Pases'!$G76,'Comisiones HEROIC'!$A$1:$B$11,2,0),15),IF('Ventas Pases'!$D76="Red HEROIC",15,0)) -> 15 | M76: =IF(pases[[#This Row],[Días Visita]]<7,0,IF(pases[[#This Row],[Días Visita]]<9,1,IF(pases[[#This Row],[Días Visita]]="Ilimitados",0,2))) -> 0 | N76: =IF(AND('Ventas Pases'!$A76="Fuera de Temporada",'Ventas Pases'!$B76=2019,pases[[#This Row],[Modo de Compra]]="Paquete"),30,0) -> 0 | O76: =-SUMIF(lift[Número de pase],pases[[#This Row],[Numero de Pase]],lift[Costo]) -> 0
A77: Temporada Regular | B77: 2019 | C77: 43549 | D77: Físico | E77: 43545 | F77: 9 | G77: Valle Silbador | H77: WSP-0076 | I77: 1080 | J77: =IFERROR('Ventas Pases'!$I77/'Ventas Pases'!$F77,"PASE") -> 120 | K77: =IFERROR(VLOOKUP('Ventas Pases'!$J77,'Comisiones HEROIC'!$E$1:$F$6,2,0),"") | L77: =IF('Ventas Pases'!$D77="Red HEROIC",IFERROR(VLOOKUP('Ventas Pases'!$G77,'Comisiones HEROIC'!$A$1:$B$11,2,0),15),IF('Ventas Pases'!$D77="Red HEROIC",15,0)) -> 0 | M77: =IF(pases[[#This Row],[Días Visita]]<7,0,IF(pases[[#This Row],[Días Visita]]<9,1,IF(pases[[#This Row],[Días Visita]]="Ilimitados",0,2))) -> 2 | N77: =IF(AND('Ventas Pases'!$A77="Fuera de Temporada",'Ventas Pases'!$B77=2019,pases[[#This Row],[Modo de Compra]]="Paquete"),30,0) -> 0 | O77: =-SUMIF(lift[Número de pase],pases[[#This Row],[Numero de Pase]],lift[Costo]) -> 0
A78: Temporada Regular | B78: 2018 | C78: 43441 | D78: En Línea | E78: 43054 | F78: Ilimitados | G78: Valle Silbador | H78: WSP-0077 | I78: 1950 | J78: =IFERROR('Ventas Pases'!$I78/'Ventas Pases'!$F78,"PASE") -> PASE | K78: =IFERROR(VLOOKUP('Ventas Pases'!$J78,'Comisiones HEROIC'!$E$1:$F$6,2,0),"") | L78: =IF('Ventas Pases'!$D78="Red HEROIC",IFERROR(VLOOKUP('Ventas Pases'!$G78,'Comisiones HEROIC'!$A$1:$B$11,2,0),15),IF('Ventas Pases'!$D78="Red HEROIC",15,0)) -> 0 | M78: =IF(pases[[#This Row],[Días Visita]]<7,0,IF(pases[[#This Row],[Días Visita]]<9,1,IF(pases[[#This Row],[Días Visita]]="Ilimitados",0,2))) -> 0 | N78: =IF(AND('Ventas Pases'!$A78="Fuera de Temporada",'Ventas Pases'!$B78=2019,pases[[#This Row],[Modo de Compra]]="Paquete"),30,0) -> 0 | O78: =-SUMIF(lift[Número de pase],pases[[#This Row],[Numero de Pase]],lift[Costo]) -> -828
A79: Temporada Regular | B79: 2018 | C79: 43432 | D79: En Línea | E79: 43167 | F79: 7 | G79: Valle Silbador | H79: WSP-0078 | I79: 840 | J79: =IFERROR('Ventas Pases'!$I79/'Ventas Pases'!$F79,"PASE") -> 120 | K79: =IFERROR(VLOOKUP('Ventas Pases'!$J79,'Comisiones HEROIC'!$E$1:$F$6,2,0),"") | L79: =IF('Ventas Pases'!$D79="Red HEROIC",IFERROR(VLOOKUP('Ventas Pases'!$G79,'Comisiones HEROIC'!$A$1:$B$11,2,0),15),IF('Ventas Pases'!$D79="Red HEROIC",15,0)) -> 0 | M79: =IF(pases[[#This Row],[Días Visita]]<7,0,IF(pases[[#This Row],[Días Visita]]<9,1,IF(pases[[#This Row],[Días Visita]]="Ilimitados",0,2))) -> 1 | N79: =IF(AND('Ventas Pases'!$A79="Fuera de Temporada",'Ventas Pases'!$B79=2019,pases[[#This Row],[Modo de Compra]]="Paquete"),30,0) -> 0 | O79: =-SUMIF(lift[Número de pase],pases[[#This Row],[Numero de Pase]],lift[Costo]) -> 0
A80: Temporada Regular | B80: 2018 | C80: 43189 | D80: En Línea | E80: 43054 | F80: Ilimitados | G80: Valle Silbador | H80: WSP-0079 | I80: 1950 | J80: =IFERROR('Ventas Pases'!$I80/'Ventas Pases'!$F80,"PASE") -> PASE | K80: =IFERROR(VLOOKUP('Ventas Pases'!$J80,'Comisiones HEROIC'!$E$1:$F$6,2,0),"") | L80: =IF('Ventas Pases'!$D80="Red HEROIC",IFERROR(VLOOKUP('Ventas Pases'!$G80,'Comisiones HEROIC'!$A$1:$B$11,2,0),15),IF('Ventas Pases'!$D80="Red HEROIC",15,0)) -> 0 | M80: =IF(pases[[#This Row],[Días Visita]]<7,0,IF(pases[[#This Row],[Días Visita]]<9,1,IF(pases[[#This Row],[Días Visita]]="Ilimitados",0,2))) -> 0 | N80: =IF(AND('Ventas Pases'!$A80="Fuera de Temporada",'Ventas Pases'!$B80=2019,pases[[#This Row],[Modo de Compra]]="Paquete"),30,0) -> 0 | O80: =-SUMIF(lift[Número de pase],pases[[#This Row],[Numero de Pase]],lift[Costo]) -> -184
A81: Fuera de Temporada | B81: 2019 | C81: 43358 | D81: Red HEROIC | E81: 43211 | F81: 2 | G81: Montaña Panadero | H81: WSP-0080 | I81: 280 | J81: =IFERROR('Ventas Pases'!$I81/'Ventas Pases'!$F81,"PASE") -> 140 | K81: =IFERROR(VLOOKUP('Ventas Pases'!$J81,'Comisiones HEROIC'!$E$1:$F$6,2,0),"") | L81: =IF('Ventas Pases'!$D81="Red HEROIC",IFERROR(VLOOKUP('Ventas Pases'!$G81,'Comisiones HEROIC'!$A$1:$B$11,2,0),15),IF('Ventas Pases'!$D81="Red HEROIC",15,0)) -> 15 | M81: =IF(pases[[#This Row],[Días Visita]]<7,0,IF(pases[[#This Row],[Días Visita]]<9,1,IF(pases[[#This Row],[Días Visita]]="Ilimitados",0,2))) -> 0 | N81: =IF(AND('Ventas Pases'!$A81="Fuera de Temporada",'Ventas Pases'!$B81=2019,pases[[#This Row],[Modo de Compra]]="Paquete"),30,0) -> 0 | O81: =-SUMIF(lift[Número de pase],pases[[#This Row],[Numero de Pase]],lift[Costo]) -> 0
A82: Fuera de Temporada | B82: 2018 | C82: 43352 | D82: En Línea | E82: 42832 | F82: 2 | G82: Valle Silbador | H82: WSP-0081 | I82: 240 | J82: =IFERROR('Ventas Pases'!$I82/'Ventas Pases'!$F82,"PASE") -> 120 | K82: =IFERROR(VLOOKUP('Ventas Pases'!$J82,'Comisiones HEROIC'!$E$1:$F$6,2,0),"") | L82: =IF('Ventas Pases'!$D82="Red HEROIC",IFERROR(VLOOKUP('Ventas Pases'!$G82,'Comisiones HEROIC'!$A$1:$B$11,2,0),15),IF('Ventas Pases'!$D82="Red HEROIC",15,0)) -> 0 | M82: =IF(pases[[#This Row],[Días Visita]]<7,0,IF(pases[[#This Row],[Días Visita]]<9,1,IF(pases[[#This Row],[Días Visita]]="Ilimitados",0,2))) -> 0 | N82: =IF(AND('Ventas Pases'!$A82="Fuera de Temporada",'Ventas Pases'!$B82=2019,pases[[#This Row],[Modo de Compra]]="Paquete"),30,0) -> 0 | O82: =-SUMIF(lift[Número de pase],pases[[#This Row],[Numero de Pase]],lift[Costo]) -> 0
A83: Temporada Regular | B83: 2019 | C83: 43456 | D83: En Línea | E83: 43469 | F83: 4 | G83: Valle Silbador | H83: WSP-0082 | I83: 480 | J83: =IFERROR('Ventas Pases'!$I83/'Ventas Pases'!$F83,"PASE") -> 120 | K83: =IFERROR(VLOOKUP('Ventas Pases'!$J83,'Comisiones HEROIC'!$E$1:$F$6,2,0),"") | L83: =IF('Ventas Pases'!$D83="Red HEROIC",IFERROR(VLOOKUP('Ventas Pases'!$G83,'Comisiones HEROIC'!$A$1:$B$11,2,0),15),IF('Ventas Pases'!$D83="Red HEROIC",15,0)) -> 0 | M83: =IF(pases[[#This Row],[Días Visita]]<7,0,IF(pases[[#This Row],[Días Visita]]<9,1,IF(pases[[#This Row],[Días Visita]]="Ilimitados",0,2))) -> 0 | N83: =IF(AND('Ventas Pases'!$A83="Fuera de Temporada",'Ventas Pases'!$B83=2019,pases[[#This Row],[Modo de Compra]]="Paquete"),30,0) -> 0 | O83: =-SUMIF(lift[Número de pase],pases[[#This Row],[Numero de Pase]],lift[Costo]) -> 0
A84: Temporada Regular | B84: 2018 | C84: 43124 | D84: En Línea | E84: 43173 | F84: 2 | G84: Valle Silbador | H84: WSP-0083 | I84: 240 | J84: =IFERROR('Ventas Pases'!$I84/'Ventas Pases'!$F84,"PASE") -> 120 | K84: =IFERROR(VLOOKUP('Ventas Pases'!$J84,'Comisiones HEROIC'!$E$1:$F$6,2,0),"") | L84: =IF('Ventas Pases'!$D84="Red HEROIC",IFERROR(VLOOKUP('Ventas Pases'!$G84,'Comisiones HEROIC'!$A$1:$B$11,2,0),15),IF('Ventas Pases'!$D84="Red HEROIC",15,0)) -> 0 | M84: =IF(pases[[#This Row],[Días Visita]]<7,0,IF(pases[[#This Row],[Días Visita]]<9,1,IF(pases[[#This Row],[Días Visita]]="Ilimitados",0,2))) -> 0 | N84: =IF(AND('Ventas Pases'!$A84="Fuera de Temporada",'Ventas Pases'!$B84=2019,pases[[#This Row],[Modo de Compra]]="Paquete"),30,0) -> 0 | O84: =-SUMIF(lift[Número de pase],pases[[#This Row],[Numero de Pase]],lift[Costo]) -> 0
A85: Fuera de Temporada | B85: 2019 | C85: 43284 | D85: En Línea | E85: 43197 | F85: 5 | G85: Valle Silbador | H85: WSP-0084 | I85: 600 | J85: =IFERROR('Ventas Pases'!$I85/'Ventas Pases'!$F85,"PASE") -> 120 | K85: =IFERROR(VLOOKUP('Ventas Pases'!$J85,'Comisiones HEROIC'!$E$1:$F$6,2,0),"") | L85: =IF('Ventas Pases'!$D85="Red HEROIC",IFERROR(VLOOKUP('Ventas Pases'!$G85,'Comisiones HEROIC'!$A$1:$B$11,2,0),15),IF('Ventas Pases'!$D85="Red HEROIC",15,0)) -> 0 | M85: =IF(pases[[#This Row],[Días Visita]]<7,0,IF(pases[[#This Row],[Días Visita]]<9,1,IF(pases[[#This Row],[Días Visita]]="Ilimitados",0,2))) -> 0 | N85: =IF(AND('Ventas Pases'!$A85="Fuera de Temporada",'Ventas Pases'!$B85=2019,pases[[#This Row],[Modo de Compra]]="Paquete"),30,0) -> 0 | O85: =-SUMIF(lift[Número de pase],pases[[#This Row],[Numero de Pase]],lift[Costo]) -> 0
A86: Temporada Regular | B86: 2019 | C86: 43486 | D86: En Línea | E86: 43541 | F86: 5 | G86: Valle Silbador | H86: WSP-0085 | I86: 600 | J86: =IFERROR('Ventas Pases'!$I86/'Ventas Pases'!$F86,"PASE") -> 120 | K86: =IFERROR(VLOOKUP('Ventas Pases'!$J86,'Comisiones HEROIC'!$E$1:$F$6,2,0),"") | L86: =IF('Ventas Pases'!$D86="Red HEROIC",IFERROR(VLOOKUP('Ventas Pases'!$G86,'Comisiones HEROIC'!$A$1:$B$11,2,0),15),IF('Ventas Pases'!$D86="Red HEROIC",15,0)) -> 0 | M86: =IF(pases[[#This Row],[Días Visita]]<7,0,IF(pases[[#This Row],[Días Visita]]<9,1,IF(pases[[#This Row],[Días Visita]]="Ilimitados",0,2))) -> 0 | N86: =IF(AND('Ventas Pases'!$A86="Fuera de Temporada",'Ventas Pases'!$B86=2019,pases[[#This Row],[Modo de Compra]]="Paquete"),30,0) -> 0 | O86: =-SUMIF(lift[Número de pase],pases[[#This Row],[Numero de Pase]],lift[Costo]) -> 0
A87: Temporada Regular | B87: 2019 | C87: 43475 | D87: Paquete | E87: 43473 | F87: 4 | G87: Valle Silbador | H87: WSP-0086 | I87: 300 | J87: =IFERROR('Ventas Pases'!$I87/'Ventas Pases'!$F87,"PASE") -> 75 | K87: =IFERROR(VLOOKUP('Ventas Pases'!$J87,'Comisiones HEROIC'!$E$1:$F$6,2,0),"") -> Ski Inn | L87: =IF('Ventas Pases'!$D87="Red HEROIC",IFERROR(VLOOKUP('Ventas Pases'!$G87,'Comisiones HEROIC'!$A$1:$B$11,2,0),15),IF('Ventas Pases'!$D87="Red HEROIC",15,0)) -> 0 | M87: =IF(pases[[#This Row],[Días Visita]]<7,0,IF(pases[[#This Row],[Días Visita]]<9,1,IF(pases[[#This Row],[Días Visita]]="Ilimitados",0,2))) -> 0 | N87: =IF(AND('Ventas Pases'!$A87="Fuera de Temporada",'Ventas Pases'!$B87=2019,pases[[#This Row],[Modo de Compra]]="Paquete"),30,0) -> 0 | O87: =-SUMIF(lift[Número de pase],pases[[#This Row],[Numero de Pase]],lift[Costo]) -> 0
A88: Fuera de Temporada | B88: 2019 | C88: 43234 | D88: En Línea | E88: 43224 | F88: 5 | G88: Valle Silbador | H88: WSP-0087 | I88: 600 | J88: =IFERROR('Ventas Pases'!$I88/'Ventas Pases'!$F88,"PASE") -> 120 | K88: =IFERROR(VLOOKUP('Ventas Pases'!$J88,'Comisiones HEROIC'!$E$1:$F$6,2,0),"") | L88: =IF('Ventas Pases'!$D88="Red HEROIC",IFERROR(VLOOKUP('Ventas Pases'!$G88,'Comisiones HEROIC'!$A$1:$B$11,2,0),15),IF('Ventas Pases'!$D88="Red HEROIC",15,0)) -> 0 | M88: =IF(pases[[#This Row],[Días Visita]]<7,0,IF(pases[[#This Row],[Días Visita]]<9,1,IF(pases[[#This Row],[Días Visita]]="Ilimitados",0,2))) -> 0 | N88: =IF(AND('Ventas Pases'!$A88="Fuera de Temporada",'Ventas Pases'!$B88=2019,pases[[#This Row],[Modo de Compra]]="Paquete"),30,0) -> 0 | O88: =-SUMIF(lift[Número de pase],pases[[#This Row],[Numero de Pase]],lift[Costo]) -> 0
A89: Temporada Regular | B89: 2019 | C89: 43520 | D89: En Línea | E89: 43529 | F89: 4 | G89: Valle Silbador | H89: WSP-0088 | I89: 480 | J89: =IFERROR('Ventas Pases'!$I89/'Ventas Pases'!$F89,"PASE") -> 120 | K89: =IFERROR(VLOOKUP('Ventas Pases'!$J89,'Comisiones HEROIC'!$E$1:$F$6,2,0),"") | L89: =IF('Ventas Pases'!$D89="Red HEROIC",IFERROR(VLOOKUP('Ventas Pases'!$G89,'Comisiones HEROIC'!$A$1:$B$11,2,0),15),IF('Ventas Pases'!$D89="Red HEROIC",15,0)) -> 0 | M89: =IF(pases[[#This Row],[Días Visita]]<7,0,IF(pases[[#This Row],[Días Visita]]<9,1,IF(pases[[#This Row],[Días Visita]]="Ilimitados",0,2))) -> 0 | N89: =IF(AND('Ventas Pases'!$A89="Fuera de Temporada",'Ventas Pases'!$B89=2019,pases[[#This Row],[Modo de Compra]]="Paquete"),30,0) -> 0 | O89: =-SUMIF(lift[Número de pase],pases[[#This Row],[Numero de Pase]],lift[Costo]) -> 0
A90: Fuera de Temporada | B90: 2019 | C90: 43392 | D90: Red HEROIC | E90: 43213 | F90: 8 | G90: Cresta Velo | H90: WSP-0089 | I90: 1120 | J90: =IFERROR('Ventas Pases'!$I90/'Ventas Pases'!$F90,"PASE") -> 140 | K90: =IFERROR(VLOOKUP('Ventas Pases'!$J90,'Comisiones HEROIC'!$E$1:$F$6,2,0),"") | L90: =IF('Ventas Pases'!$D90="Red HEROIC",IFERROR(VLOOKUP('Ventas Pases'!$G90,'Comisiones HEROIC'!$A$1:$B$11,2,0),15),IF('Ventas Pases'!$D90="Red HEROIC",15,0)) -> 15 | M90: =IF(pases[[#This Row],[Días Visita]]<7,0,IF(pases[[#This Row],[Días Visita]]<9,1,IF(pases[[#This Row],[Días Visita]]="Ilimitados",0,2))) -> 1 | N90: =IF(AND('Ventas Pases'!$A90="Fuera de Temporada",'Ventas Pases'!$B90=2019,pases[[#This Row],[Modo de Compra]]="Paquete"),30,0) -> 0 | O90: =-SUMIF(lift[Número de pase],pases[[#This Row],[Numero de Pase]],lift[Costo]) -> 0
A91: Fuera de Temporada | B91: 2018 | C91: 43364 | D91: Paquete | E91: 42890 | F91: 5 | G91: Valle Silbador | H91: WSP-0090 | I91: 550 | J91: =IFERROR('Ventas Pases'!$I91/'Ventas Pases'!$F91,"PASE") -> 110 | K91: =IFERROR(VLOOKUP('Ventas Pases'!$J91,'Comisiones HEROIC'!$E$1:$F$6,2,0),"") -> Elton Hotel | L91: =IF('Ventas Pases'!$D91="Red HEROIC",IFERROR(VLOOKUP('Ventas Pases'!$G91,'Comisiones HEROIC'!$A$1:$B$11,2,0),15),IF('Ventas Pases'!$D91="Red HEROIC",15,0)) -> 0 | M91: =IF(pases[[#This Row],[Días Visita]]<7,0,IF(pases[[#This Row],[Días Visita]]<9,1,IF(pases[[#This Row],[Días Visita]]="Ilimitados",0,2))) -> 0 | N91: =IF(AND('Ventas Pases'!$A91="Fuera de Temporada",'Ventas Pases'!$B91=2019,pases[[#This Row],[Modo de Compra]]="Paquete"),30,0) -> 0 | O91: =-SUMIF(lift[Número de pase],pases[[#This Row],[Numero de Pase]],lift[Costo]) -> 0
A92: Temporada Regular | B92: 2018 | C92: 43129 | D92: En Línea | E92: 43149 | F92: 5 | G92: Valle Silbador | H92: WSP-0091 | I92: 600 | J92: =IFERROR('Ventas Pases'!$I92/'Ventas Pases'!$F92,"PASE") -> 120 | K92: =IFERROR(VLOOKUP('Ventas Pases'!$J92,'Comisiones HEROIC'!$E$1:$F$6,2,0),"") | L92: =IF('Ventas Pases'!$D92="Red HEROIC",IFERROR(VLOOKUP('Ventas Pases'!$G92,'Comisiones HEROIC'!$A$1:$B$11,2,0),15),IF('Ventas Pases'!$D92="Red HEROIC",15,0)) -> 0 | M92: =IF(pases[[#This Row],[Días Visita]]<7,0,IF(pases[[#This Row],[Días Visita]]<9,1,IF(pases[[#This Row],[Días Visita]]="Ilimitados",0,2))) -> 0 | N92: =IF(AND('Ventas Pases'!$A92="Fuera de Temporada",'Ventas Pases'!$B92=2019,pases[[#This Row],[Modo de Compra]]="Paquete"),30,0) -> 0 | O92: =-SUMIF(lift[Número de pase],pases[[#This Row],[Numero de Pase]],lift[Costo]) -> 0
... A95: Fuera de Temporada | B95: 2019 | C95: 43384 | D95: En Línea | E95: 43208 | F95: 2 | G95: Valle Silbador | H95: WSP-0094 | I95: 240 | J95: =IFERROR('Ventas Pases'!$I95/'Ventas Pases'!$F95,"PASE") -> 120 | K95: =IFERROR(VLOOKUP('Ventas Pases'!$J95,'Comisiones HEROIC'!$E$1:$F$6,2,0),"") | L95: =IF('Ventas Pases'!$D95="Red HEROIC",IFERROR(VLOOKUP('Ventas Pases'!$G95,'Comisiones HEROIC'!$A$1:$B$11,2,0),15),IF('Ventas Pases'!$D95="Red HEROIC",15,0)) -> 0 | M95: =IF(pases[[#This Row],[Días Visita]]<7,0,IF(pases[[#This Row],[Días Visita]]<9,1,IF(pases[[#This Row],[Días Visita]]="Ilimitados",0,2))) -> 0 | N95: =IF(AND('Ventas Pases'!$A95="Fuera de Temporada",'Ventas Pases'!$B95=2019,pases[[#This Row],[Modo de Compra]]="Paquete"),30,0) -> 0 | O95: =-SUMIF(lift[Número de pase],pases[[#This Row],[Numero de Pase]],lift[Costo]) -> 0
A96: Temporada Regular | B96: 2019 | C96: 43451 | D96: Físico | E96: 43419 | F96: Ilimitados | G96: Valle Silbador | H96: WSP-0095 | I96: 1950 | J96: =IFERROR('Ventas Pases'!$I96/'Ventas Pases'!$F96,"PASE") -> PASE | K96: =IFERROR(VLOOKUP('Ventas Pases'!$J96,'Comisiones HEROIC'!$E$1:$F$6,2,0),"") | L96: =IF('Ventas Pases'!$D96="Red HEROIC",IFERROR(VLOOKUP('Ventas Pases'!$G96,'Comisiones HEROIC'!$A$1:$B$11,2,0),15),IF('Ventas Pases'!$D96="Red HEROIC",15,0)) -> 0 | M96: =IF(pases[[#This Row],[Días Visita]]<7,0,IF(pases[[#This Row],[Días Visita]]<9,1,IF(pases[[#This Row],[Días Visita]]="Ilimitados",0,2))) -> 0 | N96: =IF(AND('Ventas Pases'!$A96="Fuera de Temporada",'Ventas Pases'!$B96=2019,pases[[#This Row],[Modo de Compra]]="Paquete"),30,0) -> 0 | O96: =-SUMIF(lift[Número de pase],pases[[#This Row],[Numero de Pase]],lift[Costo]) -> -736
A97: Temporada Regular | B97: 2018 | C97: 43132 | D97: Red HEROIC | E97: 43134 | F97: 7 | G97: Cresta Velo | H97: WSP-0096 | I97: 980 | J97: =IFERROR('Ventas Pases'!$I97/'Ventas Pases'!$F97,"PASE") -> 140 | K97: =IFERROR(VLOOKUP('Ventas Pases'!$J97,'Comisiones HEROIC'!$E$1:$F$6,2,0),"") | L97: =IF('Ventas Pases'!$D97="Red HEROIC",IFERROR(VLOOKUP('Ventas Pases'!$G97,'Comisiones HEROIC'!$A$1:$B$11,2,0),15),IF('Ventas Pases'!$D97="Red HEROIC",15,0)) -> 15 | M97: =IF(pases[[#This Row],[Días Visita]]<7,0,IF(pases[[#This Row],[Días Visita]]<9,1,IF(pases[[#This Row],[Días Visita]]="Ilimitados",0,2))) -> 1 | N97: =IF(AND('Ventas Pases'!$A97="Fuera de Temporada",'Ventas Pases'!$B97=2019,pases[[#This Row],[Modo de Compra]]="Paquete"),30,0) -> 0 | O97: =-SUMIF(lift[Número de pase],pases[[#This Row],[Numero de Pase]],lift[Costo]) -> 0
A98: Temporada Regular | B98: 2018 | C98: 43448 | D98: En Línea | E98: 43075 | F98: 8 | G98: Valle Silbador | H98: WSP-0097 | I98: 960 | J98: =IFERROR('Ventas Pases'!$I98/'Ventas Pases'!$F98,"PASE") -> 120 | K98: =IFERROR(VLOOKUP('Ventas Pases'!$J98,'Comisiones HEROIC'!$E$1:$F$6,2,0),"") | L98: =IF('Ventas Pases'!$D98="Red HEROIC",IFERROR(VLOOKUP('Ventas Pases'!$G98,'Comisiones HEROIC'!$A$1:$B$11,2,0),15),IF('Ventas Pases'!$D98="Red HEROIC",15,0)) -> 0 | M98: =IF(pases[[#This Row],[Días Visita]]<7,0,IF(pases[[#This Row],[Días Visita]]<9,1,IF(pases[[#This Row],[Días Visita]]="Ilimitados",0,2))) -> 1 | N98: =IF(AND('Ventas Pases'!$A98="Fuera de Temporada",'Ventas Pases'!$B98=2019,pases[[#This Row],[Modo de Compra]]="Paquete"),30,0) -> 0 | O98: =-SUMIF(lift[Número de pase],pases[[#This Row],[Numero de Pase]],lift[Costo]) -> 0
A99: Fuera de Temporada | B99: 2019 | C99: 43311 | D99: En Línea | E99: 43419 | F99: Ilimitados | G99: Valle Silbador | H99: WSP-0098 | I99: 1950 | J99: =IFERROR('Ventas Pases'!$I99/'Ventas Pases'!$F99,"PASE") -> PASE | K99: =IFERROR(VLOOKUP('Ventas Pases'!$J99,'Comisiones HEROIC'!$E$1:$F$6,2,0),"") | L99: =IF('Ventas Pases'!$D99="Red HEROIC",IFERROR(VLOOKUP('Ventas Pases'!$G99,'Comisiones HEROIC'!$A$1:$B$11,2,0),15),IF('Ventas Pases'!$D99="Red HEROIC",15,0)) -> 0 | M99: =IF(pases[[#This Row],[Días Visita]]<7,0,IF(pases[[#This Row],[Días Visita]]<9,1,IF(pases[[#This Row],[Días Visita]]="Ilimitados",0,2))) -> 0 | N99: =IF(AND('Ventas Pases'!$A99="Fuera de Temporada",'Ventas Pases'!$B99=2019,pases[[#This Row],[Modo de Compra]]="Paquete"),30,0) -> 0 | O99: =-SUMIF(lift[Número de pase],pases[[#This Row],[Numero de Pase]],lift[Costo]) -> -184
A100: Temporada Regular | B100: 2019 | C100: 43442 | D100: En Línea | E100: 43541 | F100: 8 | G100: Valle Silbador | H100: WSP-0099 | I100: 960 | J100: =IFERROR('Ventas Pases'!$I100/'Ventas Pases'!$F100,"PASE") -> 120 | K100: =IFERROR(VLOOKUP('Ventas Pases'!$J100,'Comisiones HEROIC'!$E$1:$F$6,2,0),"") | L100: =IF('Ventas Pases'!$D100="Red HEROIC",IFERROR(VLOOKUP('Ventas Pases'!$G100,'Comisiones HEROIC'!$A$1:$B$11,2,0),15),IF('Ventas Pases'!$D100="Red HEROIC",15,0)) -> 0 | M100: =IF(pases[[#This Row],[Días Visita]]<7,0,IF(pases[[#This Row],[Días Visita]]<9,1,IF(pases[[#This Row],[Días Visita]]="Ilimitados",0,2))) -> 1 | N100: =IF(AND('Ventas Pases'!$A100="Fuera de Temporada",'Ventas Pases'!$B100=2019,pases[[#This Row],[Modo de Compra]]="Paquete"),30,0) -> 0 | O100: =-SUMIF(lift[Número de pase],pases[[#This Row],[Numero de Pase]],lift[Costo]) -> 0
A101: Temporada Regular | B101: 2019 | C101: 43432 | D101: Red HEROIC | E101: 43428 | F101: 9 | G101: Ski Comanche | H101: WSP-0100 | I101: 1260 | J101: =IFERROR('Ventas Pases'!$I101/'Ventas Pases'!$F101,"PASE") -> 140 | K101: =IFERROR(VLOOKUP('Ventas Pases'!$J101,'Comisiones HEROIC'!$E$1:$F$6,2,0),"") | L101: =IF('Ventas Pases'!$D101="Red HEROIC",IFERROR(VLOOKUP('Ventas Pases'!$G101,'Comisiones HEROIC'!$A$1:$B$11,2,0),15),IF('Ventas Pases'!$D101="Red HEROIC",15,0)) -> 15 | M101: =IF(pases[[#This Row],[Días Visita]]<7,0,IF(pases[[#This Row],[Días Visita]]<9,1,IF(pases[[#This Row],[Días Visita]]="Ilimitados",0,2))) -> 2 | N101: =IF(AND('Ventas Pases'!$A101="Fuera de Temporada",'Ventas Pases'!$B101=2019,pases[[#This Row],[Modo de Compra]]="Paquete"),30,0) -> 0 | O101: =-SUMIF(lift[Número de pase],pases[[#This Row],[Numero de Pase]],lift[Costo]) -> 0
A102: Fuera de Temporada | B102: 2018 | C102: 43232 | D102: En Línea | E102: 42950 | F102: 4 | G102: Valle Silbador | H102: WSP-0101 | I102: 480 | J102: =IFERROR('Ventas Pases'!$I102/'Ventas Pases'!$F102,"PASE") -> 120 | K102: =IFERROR(VLOOKUP('Ventas Pases'!$J102,'Comisiones HEROIC'!$E$1:$F$6,2,0),"") | L102: =IF('Ventas Pases'!$D102="Red HEROIC",IFERROR(VLOOKUP('Ventas Pases'!$G102,'Comisiones HEROIC'!$A$1:$B$11,2,0),15),IF('Ventas Pases'!$D102="Red HEROIC",15,0)) -> 0 | M102: =IF(pases[[#This Row],[Días Visita]]<7,0,IF(pases[[#This Row],[Días Visita]]<9,1,IF(pases[[#This Row],[Días Visita]]="Ilimitados",0,2))) -> 0 | N102: =IF(AND('Ventas Pases'!$A102="Fuera de Temporada",'Ventas Pases'!$B102=2019,pases[[#This Row],[Modo de Compra]]="Paquete"),30,0) -> 0 | O102: =-SUMIF(lift[Número de pase],pases[[#This Row],[Numero de Pase]],lift[Costo]) -> 0
A103: Temporada Regular | B103: 2018 | C103: 43435 | D103: Paquete | E103: 43146 | F103: 5 | G103: Valle Silbador | H103: WSP-0102 | I103: 550 | J103: =IFERROR('Ventas Pases'!$I103/'Ventas Pases'!$F103,"PASE") -> 110 | K103: =IFERROR(VLOOKUP('Ventas Pases'!$J103,'Comisiones HEROIC'!$E$1:$F$6,2,0),"") -> Elton Hotel | L103: =IF('Ventas Pases'!$D103="Red HEROIC",IFERROR(VLOOKUP('Ventas Pases'!$G103,'Comisiones HEROIC'!$A$1:$B$11,2,0),15),IF('Ventas Pases'!$D103="Red HEROIC",15,0)) -> 0 | M103: =IF(pases[[#This Row],[Días Visita]]<7,0,IF(pases[[#This Row],[Días Visita]]<9,1,IF(pases[[#This Row],[Días Visita]]="Ilimitados",0,2))) -> 0 | N103: =IF(AND('Ventas Pases'!$A103="Fuera de Temporada",'Ventas Pases'!$B103=2019,pases[[#This Row],[Modo de Compra]]="Paquete"),30,0) -> 0 | O103: =-SUMIF(lift[Número de pase],pases[[#This Row],[Numero de Pase]],lift[Costo]) -> 0
A104: Fuera de Temporada | B104: 2018 | C104: 43271 | D104: Paquete | E104: 42855 | F104: 1 | G104: Valle Silbador | H104: WSP-0103 | I104: 110 | J104: =IFERROR('Ventas Pases'!$I104/'Ventas Pases'!$F104,"PASE") -> 110 | K104: =IFERROR(VLOOKUP('Ventas Pases'!$J104,'Comisiones HEROIC'!$E$1:$F$6,2,0),"") -> Elton Hotel | L104: =IF('Ventas Pases'!$D104="Red HEROIC",IFERROR(VLOOKUP('Ventas Pases'!$G104,'Comisiones HEROIC'!$A$1:$B$11,2,0),15),IF('Ventas Pases'!$D104="Red HEROIC",15,0)) -> 0 | M104: =IF(pases[[#This Row],[Días Visita]]<7,0,IF(pases[[#This Row],[Días Visita]]<9,1,IF(pases[[#This Row],[Días Visita]]="Ilimitados",0,2))) -> 0 | N104: =IF(AND('Ventas Pases'!$A104="Fuera de Temporada",'Ventas Pases'!$B104=2019,pases[[#This Row],[Modo de Compra]]="Paquete"),30,0) -> 0 | O104: =-SUMIF(lift[Número de pase],pases[[#This Row],[Numero de Pase]],lift[Costo]) -> 0
...

Sheet Lifts Semana
A1: Fecha | B1: Hora | C1: Día de la semana | D1: Telesqui (Lift) | E1: Número de pase | F1: Costo
A2: 43423 | B2: 0.52 | C2: Lunes | D2: Góndola Principal | E2: WSP-12651 | F2: 92
A3: 43490 | B3: 0.14 | C3: Viernes | D3: Montaña Negra | E3: WSP-0386 | F3: 92
A4: 43532 | B4: 0.15 | C4: Viernes | D4: Montaña Negra | E4: WSP-14941 | F4: 92
A5: 43549 | B5: 0.12 | C5: Lunes | D5: Valle Silbador | E5: WSP-9787 | F5: 92
A6: 43507 | B6: 0.74 | C6: Lunes | D6: Riachuelo Caliente | E6: WSP-14455 | F6: 92
A7: 43536 | B7: 0.91 | C7: Martes | D7: Góndola Principal | E7: WSP-11595 | F7: 92
A8: 43501 | B8: 0.1 | C8: Martes | D8: Montaña Negra | E8: WSP-17836 | F8: 92
A9: 43444 | B9: 0.63 | C9: Lunes | D9: Cima del mundo | E9: WSP-18970 | F9: 92
A10: 43538 | B10: 0.29 | C10: Jueves | D10: Montaña Negra | E10: WSP-14285 | F10: 92
A11: 43444 | B11: 0.21 | C11: Lunes | D11: Montaña Negra | E11: WSP-9047 | F11: 92
A12: 43546 | B12: 0.64 | C12: Viernes | D12: Valle Silbador | E12: WSP-0444 | F12: 92
A13: 43538 | B13: 0.01 | C13: Jueves | D13: Valle Silbador | E13: WSP-4652 | F13: 92
... A12497: 43446 | B12497: 0.39 | C12497: Miércoles | D12497: Valle Silbador | E12497: WSP-0331 | F12497: 92

Sheet Analisis
A1: Análisis de pases
A2: Ventas totales | F2: Visitantes por modo de compra | J2: Días Visita | K2: 7
A3: Suma de Precio Venta | F3: Etiquetas de fila | G3: Cuenta de Momento de Compra
A4: 4078035 | B4: =GETPIVOTDATA("Precio Venta",$A$3) -> 4078035 | F4: En Línea | G4: 0.49269854 | J4: Suma de Dias de regalo
F5: Red HEROIC | G5: 0.25245049 | J5: 451
F6: Paquete | G6: 0.17903581
A7: Promedio de visita | F7: Físico | G7: 0.075815163
A8: Días Visita | B8: (Varios elementos) | F8: Total general | G8: 1
A10: Promedio de Días Visita
A11: 4.9905727 | B11: =GETPIVOTDATA("Días Visita",$A$10) -> 4.9905727 | F11: Visitantes por parque Red HEORIC | J11: Cuenta de Fecha | K11: Etiquetas de columna
F12: Modo de Compra | G12: Red HEROIC | J12: Etiquetas de fila | K12: Cima del mundo | L12: Góndola Principal | M12: Montaña Negra | N12: Riachuelo Caliente | O12: Valle Silbador | P12: Total general
A13: Ventas mayores a $1000 | J13: Trim.1 | K13: 509 | L13: 1518 | M13: 2408 | N13: 823 | O13: 2843 | P13: 8101
F14: Etiquetas de fila | G14: Cuenta de Momento de Compra | J14: Trim.2 | K14: 1 | L14: 19 | M14: 23 | N14: 7 | O14: 30 | P14: 80
F15: Monte Japón | G15: 0.049920761 | J15: Trim.4 | K15: 263 | L15: 879 | M15: 1307 | N15: 390 | O15: 1476 | P15: 4315
A16: Etiquetas de fila | B16: Suma de Precio Venta | F16: Ski Comanche | G16: 0.11014263 | J16: Total general | K16: 773 | L16: 2416 | M16: 3738 | N16: 1220 | O16: 4349 | P16: 12496
A17: <1000 | B17: 2004270 | C17: =GETPIVOTDATA("Precio Venta",$A$16,"Precio Venta",1000) -> 2073765 | F17: Puente Roto | G17: 0.22028526
A18: 1000-1999 | B18: 2073765 | C18: =GETPIVOTDATA("Precio Venta",$A$16,"Precio Venta",1000)/B4 -> 0.50852065 | F18: Cresta Velo | G18: 0.27020602
A19: Total general | B19: 4078035 | F19: Montaña Panadero | G19: 0.34944532
F20: Total general | G20: 1
A22: Dias de regalo
A23: Suma de Dias de regalo | F23: Viajes en lift por trimestre
A24: 1892 | B24: =GETPIVOTDATA("Dias de regalo",$A$23) -> 1892
F26: Etiquetas de fila | G26: Cuenta de Fecha
A27: Rentas | F27: Trim.1 | G27: 8101
A28: Suma de Renta | F28: Trim.2 | G28: 80
A29: 3780 | B29: =GETPIVOTDATA("Renta",$A$28) -> 3780 | F29: Trim.4 | G29: 4315
F30: Total general | G30: 12496
A32: Ganancia
A33: Días Visita | B33: Ilimitados
A34: ventas | D34: costos
A35: Suma de Precio Venta | D35: Suma de Costos lift
A36: 1474200 | D36: -284188 | F36: Cuenta de Fecha | G36: Día de la semana
F37: Número de pase | G37: Domingo | H37: Lunes | I37: Martes | J37: Miércoles | K37: Jueves | L37: Viernes | M37: Sábado | N37: Total general
A38: Ganancia | C38: Ganancias/perdidas | F38: WSP-3711 | G38: 4 | H38: 5 | I38: 4 | K38: 2 | L38: 1 | N38: 16
A39: =GETPIVOTDATA("Precio Venta",$A$35)+GETPIVOTDATA("Costos lift",$D$35) -> 1190012 | C39: =A39/-GETPIVOTDATA("Costos lift",$D$35) -> 4.1874112 | F39: WSP-13456 | G39: 1 | H39: 2 | I39: 2 | J39: 4 | K39: 1 | L39: 4 | M39: 1 | N39: 15
F40: WSP-9980 | G40: 4 | I40: 3 | J40: 2 | K40: 2 | L40: 2 | M40: 2 | N40: 15
F41: WSP-9066 | G41: 4 | H41: 3 | I41: 4 | J41: 1 | K41: 1 | L41: 1 | N41: 14
F42: WSP-9241 | G42: 3 | H42: 4 | I42: 2 | J42: 1 | K42: 2 | L42: 1 | M42: 1 | N42: 14
F43: WSP-11590 | G43: 3 | H43: 1 | J43: 1 | K43: 1 | L43: 4 | M43: 3 | N43: 13
F44: WSP-5982 | H44: 1 | I44: 1 | J44: 1 | K44: 3 | L44: 3 | M44: 4 | N44: 13
F45: WSP-9383 | G45: 1 | I45: 4 | J45: 4 | K45: 2 | L45: 2 | N45: 13
F46: WSP-13791 | G46: 1 | H46: 1 | I46: 2 | J46: 4 | K46: 2 | L46: 2 | M46: 1 | N46: 13
A47: Etiquetas de fila | B47: Suma de Precio Venta | F47: WSP-14165 | G47: 3 | H47: 1 | J47: 1 | K47: 5 | L47: 1 | M47: 2 | N47: 13
A48: En Línea | B48: 2389530 | F48: WSP-0304 | G48: 1 | H48: 3 | I48: 1 | J48: 2 | K48: 1 | M48: 5 | N48: 13
A49: Físico | B49: 331710 | F49: WSP-1768 | G49: 1 | H49: 3 | I49: 2 | J49: 1 | K49: 1 | L49: 2 | M49: 2 | N49: 12
A50: Paquete | B50: 462195 | F50: WSP-6597 | G50: 1 | H50: 4 | I50: 2 | K50: 1 | L50: 2 | M50: 2 | N50: 12
A51: Red HEROIC | B51: 894600 | F51: WSP-4267 | G51: 2 | H51: 2 | I51: 2 | J51: 3 | L51: 1 | M51: 2 | N51: 12
A52: Total general | B52: 4078035 | F52: WSP-12577 | G52: 4 | H52: 1 | I52: 1 | J52: 1 | K52: 2 | L52: 3 | N52: 12
F53: WSP-8466 | H53: 3 | I53: 2 | L53: 3 | M53: 4 | N53: 12
F54: WSP-12651 | G54: 3 | H54: 4 | J54: 1 | K54: 2 | L54: 1 | M54: 1 | N54: 12
F55: WSP-9787 | G55: 3 | H55: 2 | I55: 2 | L55: 1 | M55: 4 | N55: 12
A56: Días Visita | B56: 3 | F56: WSP-13793 | G56: 4 | I56: 1 | K56: 5 | L56: 1 | M56: 1 | N56: 12
F57: WSP-4813 | G57: 1 | H57: 2 | I57: 3 | J57: 1 | K57: 2 | L57: 2 | M57: 1 | N57: 12
A58: Etiquetas de fila | B58: Suma de Comisiones | F58: WSP-1396 | G58: 2 | H58: 2 | I58: 4 | K58: 2 | L58: 1 | M58: 1 | N58: 12
A59: Cresta Velo | B59: 585 | F59: WSP-8054 | G59: 4 | H59: 2 | I59: 1 | K59: 2 | L59: 2 | M59: 1 | N59: 12
A60: Montaña Panadero | B60: 990 | F60: WSP-14786 | G60: 3 | H60: 3 | I60: 3 | K60: 2 | M60: 1 | N60: 12
A61: Monte Japón | B61: 64 | F61: WSP-9301 | H61: 4 | I61: 1 | J61: 1 | K61: 3 | M61: 3 | N61: 12
A62: Puente Roto | B62: 336 | F62: WSP-16434 | G62: 4 | I62: 1 | J62: 1 | L62: 1 | M62: 5 | N62: 12
A63: Ski Comanche | B63: 150 | F63: WSP-5163 | G63: 1 | H63: 3 | I63: 1 | J63: 3 | K63: 2 | M63: 1 | N63: 11
A64: Valle Silbador | B64: 0 | F64: WSP-14186 | G64: 1 | H64: 1 | I64: 1 | J64: 2 | K64: 4 | L64: 1 | M64: 1 | N64: 11
A65: Total general | B65: 2125 | F65: WSP-7040 | G65: 1 | H65: 2 | J65: 4 | K65: 1 | L65: 3 | N65: 11
F66: WSP-11924 | G66: 1 | H66: 2 | I66: 2 | J66: 1 | K66: 2 | L66: 1 | M66: 2 | N66: 11
F67: WSP-13711 | G67: 2 | H67: 2 | I67: 2 | J67: 3 | K67: 1 | M67: 1 | N67: 11
F68: WSP-16006 | G68: 2 | H68: 1 | I68: 1 | J68: 2 | L68: 3 | M68: 2 | N68: 11
F69: WSP-0805 | H69: 3 | I69: 2 | J69: 1 | K69: 2 | L69: 2 | M69: 1 | N69: 11
F70: WSP-16122 | H70: 2 | I70: 2 | J70: 1 | L70: 2 | M70: 4 | N70: 11
F71: WSP-7398 | G71: 2 | H71: 2 | J71: 3 | K71: 1 | M71: 3 | N71: 11
F72: WSP-13142 | G72: 2 | H72: 1 | J72: 1 | K72: 3 | L72: 2 | M72: 2 | N72: 11
F73: WSP-3882 | H73: 3 | I73: 1 | J73: 2 | K73: 2 | L73: 1 | M73: 2 | N73: 11
F74: WSP-10582 | G74: 1 | H74: 1 | I74: 3 | J74: 1 | K74: 4 | L74: 1 | N74: 11
F75: WSP-0733 | G75: 2 | H75: 1 | I75: 2 | J75: 2 | K75: 2 | L75: 1 | M75: 1 | N75: 11
F76: WSP-17034 | G76: 1 | H76: 1 | I76: 2 | K76: 3 | L76: 1 | M76: 3 | N76: 11
F77: WSP-5886 | G77: 2 | H77: 3 | I77: 1 | J77: 1 | K77: 1 | L77: 1 | M77: 2 | N77: 11
F78: WSP-13238 | G78: 1 | H78: 2 | I78: 2 | J78: 1 | K78: 1 | L78: 1 | M78: 3 | N78: 11
F79: WSP-12041 | G79: 4 | H79: 1 | I79: 3 | K79: 2 | M79: 1 | N79: 11
F80: WSP-13252 | G80: 1 | H80: 2 | I80: 2 | J80: 3 | K80: 2 | L80: 1 | N80: 11
F81: WSP-7205 | G81: 2 | I81: 3 | J81: 1 | K81: 1 | L81: 2 | M81: 2 | N81: 11
F82: WSP-19180 | G82: 2 | H82: 1 | I82: 1 | J82: 3 | K82: 1 | L82: 1 | M82: 2 | N82: 11
F83: WSP-0537 | G83: 3 | H83: 1 | I83: 1 | J83: 3 | K83: 1 | L83: 2 | N83: 11
F84: WSP-2255 | G84: 4 | H84: 2 | I84: 1 | K84: 3 | M84: 1 | N84: 11
F85: WSP-14455 | G85: 2 | H85: 2 | I85: 1 | J85: 2 | K85: 1 | M85: 3 | N85: 11
F86: WSP-2892 | G86: 3 | H86: 2 | I86: 1 | J86: 1 | K86: 1 | L86: 1 | M86: 2 | N86: 11
F87: WSP-16652 | G87: 3 | H87: 2 | I87: 1 | J87: 2 | K87: 2 | L87: 1 | N87: 11
F88: WSP-19102 | G88: 1 | H88: 1 | I88: 3 | J88: 3 | K88: 1 | L88: 2 | N88: 11
F89: WSP-5743 | G89: 2 | I89: 1 | J89: 3 | K89: 1 | L89: 1 | M89: 2 | N89: 10
F90: WSP-3871 | G90: 3 | H90: 1 | I90: 1 | J90: 2 | K90: 1 | L90: 2 | N90: 10
F91: WSP-8577 | H91: 2 | I91: 2 | J91: 1 | K91: 2 | L91: 2 | M91: 1 | N91: 10
F92: WSP-15223 | G92: 1 | H92: 1 | I92: 3 | J92: 2 | K92: 1 | L92: 1 | M92: 1 | N92: 10
F93: WSP-4376 | G93: 1 | H93: 2 | I93: 1 | K93: 4 | L93: 1 | M93: 1 | N93: 10
F94: WSP-15297 | G94: 1 | H94: 4 | I94: 1 | J94: 2 | K94: 1 | M94: 1 | N94: 10
F95: WSP-7440 | G95: 1 | H95: 1 | I95: 3 | J95: 1 | K95: 1 | L95: 1 | M95: 2 | N95: 10
F96: WSP-15712 | G96: 3 | H96: 3 | J96: 1 | M96: 3 | N96: 10
F97: WSP-3076 | H97: 1 | I97: 3 | J97: 1 | K97: 1 | L97: 1 | M97: 3 | N97: 10
F98: WSP-15822 | G98: 1 | H98: 3 | I98: 2 | J98: 1 | K98: 2 | L98: 1 | N98: 10
F99: WSP-4011 | H99: 2 | I99: 1 | J99: 2 | K99: 2 | L99: 1 | M99: 2 | N99: 10
F100: WSP-16098 | G100: 3 | H100: 1 | I100: 2 | K100: 1 | L100: 1 | M100: 2 | N100: 10
F101: WSP-5577 | G101: 3 | H101: 1 | I101: 1 | J101: 1 | K101: 1 | M101: 3 | N101: 10
F102: WSP-16197 | H102: 1 | I102: 2 | L102: 6 | M102: 1 | N102: 10
F103: WSP-6082 | G103: 2 | H103: 1 | I103: 1 | J103: 1 | L103: 3 | M103: 2 | N103: 10
F104: WSP-11672 | G104: 6 | K104: 2 | L104: 1 | M104: 1 | N104: 10
...

Sheet Dashboard
E13: Ventas por Hotel
E14: Modo de Compra | F14: Paquete
E16: Hotel | F16: Ventas
E17: Elton Hotel | F17: 244200
E18: Haiit Hotel | F18: 8855
E19: OI Hotels | F19: 113190
E20: Ridossan Hotel | F20: 78400
E21: Ski Inn | F21: 17550
E22: Total general | F22: 462195
E26: Comisiones por pagar | H26: Viajes del 33% de los mejores esquiadores
E27: Modo de Compra | F27: Red HEROIC
E29: Parque | F29: Comisión | H29: Dia de la semana | I29: Cantidad
E30: Montaña Panadero | F30: 6615 | H30: Domingo | I30: 620
E31: Cresta Velo | F31: 5115 | H31: Lunes | I31: 604
E32: Puente Roto | F32: 3336 | H32: Martes | I32: 580
E33: Ski Comanche | F33: 2085 | H33: Miércoles | I33: 566
E34: Monte Japón | F34: 1008 | H34: Jueves | I34: 567
E35: Total general | F35: 18159 | H35: Viernes | I35: 584
H36: Sábado | I36: 607
H37: Total | I37: =SUM(I30:I36) -> 4128
C41: Realizado por:
C42: Gabriel Quezada
